<?xml version="1.0" standalone="yes"?>
<NewDataSet>
  <xs:schema id="NewDataSet" xmlns="" xmlns:xs="http://www.w3.org/2001/XMLSchema" xmlns:msdata="urn:schemas-microsoft-com:xml-msdata" xmlns:msprop="urn:schemas-microsoft-com:xml-msprop">
    <xs:element name="NewDataSet" msdata:IsDataSet="true" msdata:MainDataTable="Limitation" msdata:UseCurrentLocale="true">
      <xs:complexType>
        <xs:choice minOccurs="0" maxOccurs="unbounded">
          <xs:element name="Limitation" msprop:DataAdapter="System.Data.Odbc.OdbcDataAdapter">
            <xs:complexType>
              <xs:sequence>
                <xs:element name="LimitationKey" msdata:Caption="Инвентарный номер ограничения схемы дискриминации" type="xs:int" default="0" minOccurs="0" />
                <xs:element name="LimitationObjectType" msdata:Caption="тип объекта ограничений" type="xs:int" default="0" minOccurs="0" />
                <xs:element name="LimitationObjectKey" msdata:Caption="Ключ объекта ограничений" type="xs:int" default="0" minOccurs="0" />
                <xs:element name="LimitationValue" msdata:Caption="Значение органичения" type="xs:string" default="" minOccurs="0" />
                <xs:element name="LimitationType" msdata:Caption="Тип ограничения" type="xs:int" default="0" minOccurs="0" />
                <xs:element name="ActionType" msdata:Caption="Тип действия ограничения" type="xs:int" default="0" minOccurs="0" />
                <xs:element name="LimitationName" type="xs:string" default="" minOccurs="0" />
                <xs:element name="Code1" type="xs:int" default="0" minOccurs="0" />
                <xs:element name="Code2" msdata:Caption="Code2(test)" type="xs:int" default="0" minOccurs="0" />
                <xs:element name="Code3" type="xs:int" default="0" minOccurs="0" />
                <xs:element name="StartDatetime" type="xs:dateTime" default="1900-01-01T00:00:00+06:00" minOccurs="0" />
                <xs:element name="StopDatetime" type="xs:dateTime" default="9999-12-31T00:00:00+07:00" minOccurs="0" />
              </xs:sequence>
            </xs:complexType>
          </xs:element>
        </xs:choice>
      </xs:complexType>
    </xs:element>
  </xs:schema>
  <Limitation>
    <LimitationKey>1</LimitationKey>
    <LimitationObjectType>7</LimitationObjectType>
    <LimitationObjectKey>11</LimitationObjectKey>
    <LimitationValue>(1)</LimitationValue>
    <LimitationType>5</LimitationType>
    <ActionType>1</ActionType>
    <LimitationName />
    <Code1>0</Code1>
    <Code2>0</Code2>
    <Code3>0</Code3>
    <StartDatetime>1900-01-01T00:00:00+06:00</StartDatetime>
    <StopDatetime>9999-12-31T00:00:00+07:00</StopDatetime>
  </Limitation>
  <Limitation>
    <LimitationKey>2</LimitationKey>
    <LimitationObjectType>7</LimitationObjectType>
    <LimitationObjectKey>12</LimitationObjectKey>
    <LimitationValue>(1)</LimitationValue>
    <LimitationType>5</LimitationType>
    <ActionType>1</ActionType>
    <LimitationName />
    <Code1>0</Code1>
    <Code2>0</Code2>
    <Code3>0</Code3>
    <StartDatetime>1900-01-01T00:00:00+06:00</StartDatetime>
    <StopDatetime>9999-12-31T00:00:00+07:00</StopDatetime>
  </Limitation>
  <Limitation>
    <LimitationKey>14675</LimitationKey>
    <LimitationObjectType>4</LimitationObjectType>
    <LimitationObjectKey>77</LimitationObjectKey>
    <LimitationValue>(1,3,4,5,9,10,11,12,13,14,17,18,20,33,40)</LimitationValue>
    <LimitationType>5</LimitationType>
    <ActionType>1</ActionType>
    <LimitationName />
    <Code1>54001</Code1>
    <Code2>0</Code2>
    <Code3>0</Code3>
    <StartDatetime>1900-01-01T00:00:00+06:00</StartDatetime>
    <StopDatetime>9999-12-31T00:00:00+07:00</StopDatetime>
  </Limitation>
  <Limitation>
    <LimitationKey>14676</LimitationKey>
    <LimitationObjectType>4</LimitationObjectType>
    <LimitationObjectKey>77</LimitationObjectKey>
    <LimitationValue>185.62.101.94:1333</LimitationValue>
    <LimitationType>48</LimitationType>
    <ActionType>1</ActionType>
    <LimitationName />
    <Code1>54001</Code1>
    <Code2>0</Code2>
    <Code3>0</Code3>
    <StartDatetime>1900-01-01T00:00:00+06:00</StartDatetime>
    <StopDatetime>9999-12-31T00:00:00+07:00</StopDatetime>
  </Limitation>
  <Limitation>
    <LimitationKey>229701</LimitationKey>
    <LimitationObjectType>3</LimitationObjectType>
    <LimitationObjectKey>4952</LimitationObjectKey>
    <LimitationValue>(54901,54902,54903,54904,54905,54906,54907,54908,54909,54910,54911,54912,54913,54914,54915,54916,54917,54918)</LimitationValue>
    <LimitationType>2</LimitationType>
    <ActionType>2</ActionType>
    <LimitationName />
    <Code1>175</Code1>
    <Code2>4950</Code2>
    <Code3>0</Code3>
    <StartDatetime>1900-01-01T00:00:00+06:00</StartDatetime>
    <StopDatetime>9999-12-31T00:00:00+07:00</StopDatetime>
  </Limitation>
  <Limitation>
    <LimitationKey>60590</LimitationKey>
    <LimitationObjectType>11</LimitationObjectType>
    <LimitationObjectKey>420131</LimitationObjectKey>
    <LimitationValue>(22103)</LimitationValue>
    <LimitationType>2</LimitationType>
    <ActionType>1</ActionType>
    <LimitationName />
    <Code1>175</Code1>
    <Code2>4898</Code2>
    <Code3>13</Code3>
    <StartDatetime>1900-01-01T00:00:00+06:00</StartDatetime>
    <StopDatetime>9999-12-31T00:00:00+07:00</StopDatetime>
  </Limitation>
  <Limitation>
    <LimitationKey>61063</LimitationKey>
    <LimitationObjectType>3</LimitationObjectType>
    <LimitationObjectKey>4947</LimitationObjectKey>
    <LimitationValue>(22103)</LimitationValue>
    <LimitationType>2</LimitationType>
    <ActionType>1</ActionType>
    <LimitationName />
    <Code1>175</Code1>
    <Code2>4945</Code2>
    <Code3>0</Code3>
    <StartDatetime>1900-01-01T00:00:00+06:00</StartDatetime>
    <StopDatetime>9999-12-31T00:00:00+07:00</StopDatetime>
  </Limitation>
  <Limitation>
    <LimitationKey>61019</LimitationKey>
    <LimitationObjectType>11</LimitationObjectType>
    <LimitationObjectKey>426200</LimitationObjectKey>
    <LimitationValue>(22103)</LimitationValue>
    <LimitationType>2</LimitationType>
    <ActionType>1</ActionType>
    <LimitationName />
    <Code1>175</Code1>
    <Code2>0</Code2>
    <Code3>0</Code3>
    <StartDatetime>1900-01-01T00:00:00+06:00</StartDatetime>
    <StopDatetime>9999-12-31T00:00:00+07:00</StopDatetime>
  </Limitation>
  <Limitation>
    <LimitationKey>229700</LimitationKey>
    <LimitationObjectType>11</LimitationObjectType>
    <LimitationObjectKey>457582</LimitationObjectKey>
    <LimitationValue>(54012,54085)</LimitationValue>
    <LimitationType>2</LimitationType>
    <ActionType>1</ActionType>
    <LimitationName />
    <Code1>175</Code1>
    <Code2>4897</Code2>
    <Code3>204</Code3>
    <StartDatetime>1900-01-01T00:00:00+06:00</StartDatetime>
    <StopDatetime>9999-12-31T00:00:00+07:00</StopDatetime>
  </Limitation>
  <Limitation>
    <LimitationKey>56770</LimitationKey>
    <LimitationObjectType>3</LimitationObjectType>
    <LimitationObjectKey>4904</LimitationObjectKey>
    <LimitationValue>(19208,19212,19213)</LimitationValue>
    <LimitationType>2</LimitationType>
    <ActionType>1</ActionType>
    <LimitationName />
    <Code1>175</Code1>
    <Code2>4902</Code2>
    <Code3>0</Code3>
    <StartDatetime>1900-01-01T00:00:00+06:00</StartDatetime>
    <StopDatetime>9999-12-31T00:00:00+07:00</StopDatetime>
  </Limitation>
  <Limitation>
    <LimitationKey>56773</LimitationKey>
    <LimitationObjectType>3</LimitationObjectType>
    <LimitationObjectKey>4903</LimitationObjectKey>
    <LimitationValue>(19201,19207,19208,19211,19212,19213,70064,70065,70073,70074,70075,70076,70077,70078,70079,70086)</LimitationValue>
    <LimitationType>2</LimitationType>
    <ActionType>1</ActionType>
    <LimitationName />
    <Code1>175</Code1>
    <Code2>4901</Code2>
    <Code3>0</Code3>
    <StartDatetime>1900-01-01T00:00:00+06:00</StartDatetime>
    <StopDatetime>9999-12-31T00:00:00+07:00</StopDatetime>
  </Limitation>
  <Limitation>
    <LimitationKey>229412</LimitationKey>
    <LimitationObjectType>11</LimitationObjectType>
    <LimitationObjectKey>453188</LimitationObjectKey>
    <LimitationValue>(42031)</LimitationValue>
    <LimitationType>2</LimitationType>
    <ActionType>1</ActionType>
    <LimitationName />
    <Code1>175</Code1>
    <Code2>6794</Code2>
    <Code3>1</Code3>
    <StartDatetime>1900-01-01T00:00:00+06:00</StartDatetime>
    <StopDatetime>9999-12-31T00:00:00+07:00</StopDatetime>
  </Limitation>
  <Limitation>
    <LimitationKey>57206</LimitationKey>
    <LimitationObjectType>3</LimitationObjectType>
    <LimitationObjectKey>4921</LimitationObjectKey>
    <LimitationValue>(42015,42016,42018,42020,42021,42022,42023,42025,42026,42027,42028,42029,42030,42152,42153,42155,42157,42158,42159,42160,42162,42163,42164,42165,42166)</LimitationValue>
    <LimitationType>2</LimitationType>
    <ActionType>1</ActionType>
    <LimitationName />
    <Code1>175</Code1>
    <Code2>4919</Code2>
    <Code3>0</Code3>
    <StartDatetime>1900-01-01T00:00:00+06:00</StartDatetime>
    <StopDatetime>9999-12-31T00:00:00+07:00</StopDatetime>
  </Limitation>
  <Limitation>
    <LimitationKey>60591</LimitationKey>
    <LimitationObjectType>11</LimitationObjectType>
    <LimitationObjectKey>420131</LimitationObjectKey>
    <LimitationValue>(333,555,776,777,1111,11111,19201,19207,19208,19211,19212,19213,22104,22105,22107,22108,22109,22110,22111,22113,22114,22115,22116,22118,22119,22120,22121,22122,22123,22124,22125,22126,22127,22128,22129,22130,22131,22132,22133,22135,22136,22137,22139,22140,22141,22142,22143,22144,22145,22146,22147,22148,22149,22150,22151,22168,22170,22171,22172,22173,22175,22176,22177,22178,22179,22180,22181,22182,22184,22185,22189,22190,22191,22193,22195,22197,22222,22501,22502,22503,22801,22802,24001,33333,38001,38002,38003,38004,38006,38007,38008,38017,38101,38102,38103,38104,38105,38106,38108,38109,42014,42015,42016,42018,42020,42021,42022,42023,42025,42026,42027,42028,42029,42030,42032,42152,42153,42155,42157,42158,42159,42160,42162,42163,42164,42165,42166,54001,54002,54003,54004,54005,54006,54007,54008,54010,54011,54012,54013,54014,54015,54016,54017,54019,54020,54021,54022,54024,54025,54026,54027,54028,54029,54030,54031,54032,54034,54035,54036,54037,54038,54039,54040,54041,54043,54044,54047,54050,54051,54052,54055,54056,54057,54058,54060,54061,54064,54066,54080,54081,54083,54084,54085,54086,54087,54088,54089,54090,54091,54092,54704,54715,54901,54902,54903,54904,54905,54906,54907,54908,54909,54910,54911,54912,54913,54914,54915,55001,55013,70064,70065,70068,70070,70072,70073,70074,70075,70076,70077,70078,70079,70901)</LimitationValue>
    <LimitationType>2</LimitationType>
    <ActionType>2</ActionType>
    <LimitationName />
    <Code1>175</Code1>
    <Code2>4898</Code2>
    <Code3>13</Code3>
    <StartDatetime>1900-01-01T00:00:00+06:00</StartDatetime>
    <StopDatetime>9999-12-31T00:00:00+07:00</StopDatetime>
  </Limitation>
  <Limitation>
    <LimitationKey>61020</LimitationKey>
    <LimitationObjectType>11</LimitationObjectType>
    <LimitationObjectKey>426200</LimitationObjectKey>
    <LimitationValue>(333,555,776,777,1111,11111,19201,19207,19208,19211,19212,19213,22104,22105,22107,22108,22109,22110,22111,22113,22114,22115,22116,22118,22119,22120,22121,22122,22123,22124,22125,22126,22127,22128,22129,22130,22131,22132,22133,22135,22136,22137,22139,22140,22141,22142,22143,22144,22145,22146,22147,22148,22149,22150,22151,22168,22170,22171,22172,22173,22175,22176,22177,22178,22179,22180,22181,22182,22184,22185,22189,22190,22191,22193,22195,22197,22222,22501,22502,22503,22801,22802,24001,33333,38001,38002,38003,38004,38006,38007,38008,38017,38101,38102,38103,38104,38105,38106,38108,38109,42014,42015,42016,42018,42020,42021,42022,42023,42025,42026,42027,42028,42029,42030,42032,42152,42153,42155,42157,42158,42159,42160,42162,42163,42164,42165,42166,54001,54002,54003,54004,54005,54006,54007,54008,54010,54011,54012,54013,54014,54015,54016,54017,54019,54020,54021,54022,54024,54025,54026,54027,54028,54029,54030,54031,54032,54034,54035,54036,54037,54038,54039,54040,54041,54043,54044,54047,54050,54051,54052,54055,54056,54057,54058,54060,54061,54064,54066,54080,54081,54083,54084,54085,54086,54087,54088,54089,54090,54091,54092,54704,54715,54901,54902,54903,54904,54905,54906,54907,54908,54909,54910,54911,54912,54913,54914,54915,55001,55013,70064,70065,70068,70070,70072,70073,70074,70075,70076,70077,70078,70079,70901)</LimitationValue>
    <LimitationType>2</LimitationType>
    <ActionType>2</ActionType>
    <LimitationName />
    <Code1>175</Code1>
    <Code2>0</Code2>
    <Code3>0</Code3>
    <StartDatetime>1900-01-01T00:00:00+06:00</StartDatetime>
    <StopDatetime>9999-12-31T00:00:00+07:00</StopDatetime>
  </Limitation>
  <Limitation>
    <LimitationKey>61029</LimitationKey>
    <LimitationObjectType>11</LimitationObjectType>
    <LimitationObjectKey>425431</LimitationObjectKey>
    <LimitationValue>(22103)</LimitationValue>
    <LimitationType>2</LimitationType>
    <ActionType>1</ActionType>
    <LimitationName />
    <Code1>175</Code1>
    <Code2>4945</Code2>
    <Code3>1</Code3>
    <StartDatetime>1900-01-01T00:00:00+06:00</StartDatetime>
    <StopDatetime>9999-12-31T00:00:00+07:00</StopDatetime>
  </Limitation>
  <Limitation>
    <LimitationKey>61030</LimitationKey>
    <LimitationObjectType>11</LimitationObjectType>
    <LimitationObjectKey>425431</LimitationObjectKey>
    <LimitationValue>(333,555,776,777,1111,11111,19201,19207,19208,19211,19212,19213,22104,22105,22107,22108,22109,22110,22111,22113,22114,22115,22116,22118,22119,22120,22121,22122,22123,22124,22125,22126,22127,22128,22129,22130,22131,22132,22133,22135,22136,22137,22139,22140,22141,22142,22143,22144,22145,22146,22147,22148,22149,22150,22151,22168,22170,22171,22172,22173,22175,22176,22177,22178,22179,22180,22181,22182,22184,22185,22189,22190,22191,22193,22195,22197,22222,22501,22502,22503,22801,22802,24001,33333,38001,38002,38003,38004,38006,38007,38008,38017,38101,38102,38103,38104,38105,38106,38108,38109,42014,42015,42016,42018,42020,42021,42022,42023,42025,42026,42027,42028,42029,42030,42032,42152,42153,42155,42157,42158,42159,42160,42162,42163,42164,42165,42166,54001,54002,54003,54004,54005,54006,54007,54008,54010,54011,54012,54013,54014,54015,54016,54017,54019,54020,54021,54022,54024,54025,54026,54027,54028,54029,54030,54031,54032,54034,54035,54036,54037,54038,54039,54040,54041,54043,54044,54047,54050,54051,54052,54055,54056,54057,54058,54060,54061,54064,54066,54080,54081,54083,54084,54085,54086,54087,54088,54089,54090,54091,54092,54704,54715,54901,54902,54903,54904,54905,54906,54907,54908,54909,54910,54911,54912,54913,54914,54915,55001,55013,70064,70065,70068,70070,70072,70073,70074,70075,70076,70077,70078,70079,70901)</LimitationValue>
    <LimitationType>2</LimitationType>
    <ActionType>2</ActionType>
    <LimitationName />
    <Code1>175</Code1>
    <Code2>4945</Code2>
    <Code3>1</Code3>
    <StartDatetime>1900-01-01T00:00:00+06:00</StartDatetime>
    <StopDatetime>9999-12-31T00:00:00+07:00</StopDatetime>
  </Limitation>
  <Limitation>
    <LimitationKey>61065</LimitationKey>
    <LimitationObjectType>3</LimitationObjectType>
    <LimitationObjectKey>4960</LimitationObjectKey>
    <LimitationValue>(54039)</LimitationValue>
    <LimitationType>2</LimitationType>
    <ActionType>1</ActionType>
    <LimitationName />
    <Code1>175</Code1>
    <Code2>4958</Code2>
    <Code3>0</Code3>
    <StartDatetime>1900-01-01T00:00:00+06:00</StartDatetime>
    <StopDatetime>9999-12-31T00:00:00+07:00</StopDatetime>
  </Limitation>
  <Limitation>
    <LimitationKey>61066</LimitationKey>
    <LimitationObjectType>3</LimitationObjectType>
    <LimitationObjectKey>4961</LimitationObjectKey>
    <LimitationValue>(22113)</LimitationValue>
    <LimitationType>2</LimitationType>
    <ActionType>1</ActionType>
    <LimitationName />
    <Code1>175</Code1>
    <Code2>4959</Code2>
    <Code3>0</Code3>
    <StartDatetime>1900-01-01T00:00:00+06:00</StartDatetime>
    <StopDatetime>9999-12-31T00:00:00+07:00</StopDatetime>
  </Limitation>
  <Limitation>
    <LimitationKey>61476</LimitationKey>
    <LimitationObjectType>3</LimitationObjectType>
    <LimitationObjectKey>4964</LimitationObjectKey>
    <LimitationValue>(42016)</LimitationValue>
    <LimitationType>2</LimitationType>
    <ActionType>1</ActionType>
    <LimitationName />
    <Code1>175</Code1>
    <Code2>4962</Code2>
    <Code3>0</Code3>
    <StartDatetime>1900-01-01T00:00:00+06:00</StartDatetime>
    <StopDatetime>9999-12-31T00:00:00+07:00</StopDatetime>
  </Limitation>
  <Limitation>
    <LimitationKey>61509</LimitationKey>
    <LimitationObjectType>11</LimitationObjectType>
    <LimitationObjectKey>426792</LimitationObjectKey>
    <LimitationValue>(22103,22104,22105,22107,22108,22109,22110,22111,22113,22114,22115,22116,22118,22119,22120,22121,22122,22123,22124,22125,22126,22127,22128,22129,22130,22131,22132,22133,22135,22136,22137,22139,22140,22141,22142,22143,22144,22145,22146,22147,22148,22149,22150,22151,22168,22170,22171,22172,22173,22175,22176,22177,22178,22179,22180,22181,22182,22184,22185,22189,22190,22191,22193,22195,22197,22222,22501,22502,22503,22801,22802)</LimitationValue>
    <LimitationType>2</LimitationType>
    <ActionType>1</ActionType>
    <LimitationName />
    <Code1>175</Code1>
    <Code2>4897</Code2>
    <Code3>137</Code3>
    <StartDatetime>1900-01-01T00:00:00+06:00</StartDatetime>
    <StopDatetime>9999-12-31T00:00:00+07:00</StopDatetime>
  </Limitation>
  <Limitation>
    <LimitationKey>61510</LimitationKey>
    <LimitationObjectType>11</LimitationObjectType>
    <LimitationObjectKey>426793</LimitationObjectKey>
    <LimitationValue>(22103,22104,22105,22107,22108,22109,22110,22111,22113,22114,22115,22116,22118,22119,22120,22121,22122,22123,22124,22125,22126,22127,22128,22129,22130,22131,22132,22133,22135,22136,22137,22139,22140,22141,22142,22143,22144,22145,22146,22147,22148,22149,22150,22151,22168,22170,22171,22172,22173,22175,22176,22177,22178,22179,22180,22181,22182,22184,22185,22189,22190,22191,22193,22195,22197,22222,22501,22502,22503,22801,22802)</LimitationValue>
    <LimitationType>2</LimitationType>
    <ActionType>1</ActionType>
    <LimitationName />
    <Code1>175</Code1>
    <Code2>4897</Code2>
    <Code3>138</Code3>
    <StartDatetime>1900-01-01T00:00:00+06:00</StartDatetime>
    <StopDatetime>9999-12-31T00:00:00+07:00</StopDatetime>
  </Limitation>
  <Limitation>
    <LimitationKey>61511</LimitationKey>
    <LimitationObjectType>11</LimitationObjectType>
    <LimitationObjectKey>426794</LimitationObjectKey>
    <LimitationValue>(22103,22104,22105,22107,22108,22109,22110,22111,22113,22114,22115,22116,22118,22119,22120,22121,22122,22123,22124,22125,22126,22127,22128,22129,22130,22131,22132,22133,22135,22136,22137,22139,22140,22141,22142,22143,22144,22145,22146,22147,22148,22149,22150,22151,22168,22170,22171,22172,22173,22175,22176,22177,22178,22179,22180,22181,22182,22184,22185,22189,22190,22191,22193,22195,22197,22222,22501,22502,22503,22801,22802)</LimitationValue>
    <LimitationType>2</LimitationType>
    <ActionType>1</ActionType>
    <LimitationName />
    <Code1>175</Code1>
    <Code2>4897</Code2>
    <Code3>139</Code3>
    <StartDatetime>1900-01-01T00:00:00+06:00</StartDatetime>
    <StopDatetime>9999-12-31T00:00:00+07:00</StopDatetime>
  </Limitation>
  <Limitation>
    <LimitationKey>61512</LimitationKey>
    <LimitationObjectType>11</LimitationObjectType>
    <LimitationObjectKey>426795</LimitationObjectKey>
    <LimitationValue>(22103,22104,22105,22107,22108,22109,22110,22111,22113,22114,22115,22116,22118,22119,22120,22121,22122,22123,22124,22125,22126,22127,22128,22129,22130,22131,22132,22133,22135,22136,22137,22139,22140,22141,22142,22143,22144,22145,22146,22147,22148,22149,22150,22151,22168,22170,22171,22172,22173,22175,22176,22177,22178,22179,22180,22181,22182,22184,22185,22189,22190,22191,22193,22195,22197,22222,22501,22502,22503,22801,22802)</LimitationValue>
    <LimitationType>2</LimitationType>
    <ActionType>1</ActionType>
    <LimitationName />
    <Code1>175</Code1>
    <Code2>4897</Code2>
    <Code3>140</Code3>
    <StartDatetime>1900-01-01T00:00:00+06:00</StartDatetime>
    <StopDatetime>9999-12-31T00:00:00+07:00</StopDatetime>
  </Limitation>
  <Limitation>
    <LimitationKey>61513</LimitationKey>
    <LimitationObjectType>11</LimitationObjectType>
    <LimitationObjectKey>426796</LimitationObjectKey>
    <LimitationValue>(22103,22104,22105,22107,22108,22109,22110,22111,22113,22114,22115,22116,22118,22119,22120,22121,22122,22123,22124,22125,22126,22127,22128,22129,22130,22131,22132,22133,22135,22136,22137,22139,22140,22141,22142,22143,22144,22145,22146,22147,22148,22149,22150,22151,22168,22170,22171,22172,22173,22175,22176,22177,22178,22179,22180,22181,22182,22184,22185,22189,22190,22191,22193,22195,22197,22222,22501,22502,22503,22801,22802)</LimitationValue>
    <LimitationType>2</LimitationType>
    <ActionType>1</ActionType>
    <LimitationName />
    <Code1>175</Code1>
    <Code2>4897</Code2>
    <Code3>141</Code3>
    <StartDatetime>1900-01-01T00:00:00+06:00</StartDatetime>
    <StopDatetime>9999-12-31T00:00:00+07:00</StopDatetime>
  </Limitation>
  <Limitation>
    <LimitationKey>61514</LimitationKey>
    <LimitationObjectType>11</LimitationObjectType>
    <LimitationObjectKey>426797</LimitationObjectKey>
    <LimitationValue>(22103,22104,22105,22107,22108,22109,22110,22111,22113,22114,22115,22116,22118,22119,22120,22121,22122,22123,22124,22125,22126,22127,22128,22129,22130,22131,22132,22133,22135,22136,22137,22139,22140,22141,22142,22143,22144,22145,22146,22147,22148,22149,22150,22151,22168,22170,22171,22172,22173,22175,22176,22177,22178,22179,22180,22181,22182,22184,22185,22189,22190,22191,22193,22195,22197,22222,22501,22502,22503,22801,22802)</LimitationValue>
    <LimitationType>2</LimitationType>
    <ActionType>1</ActionType>
    <LimitationName />
    <Code1>175</Code1>
    <Code2>4897</Code2>
    <Code3>142</Code3>
    <StartDatetime>1900-01-01T00:00:00+06:00</StartDatetime>
    <StopDatetime>9999-12-31T00:00:00+07:00</StopDatetime>
  </Limitation>
  <Limitation>
    <LimitationKey>61507</LimitationKey>
    <LimitationObjectType>11</LimitationObjectType>
    <LimitationObjectKey>426790</LimitationObjectKey>
    <LimitationValue>(22103,22104,22105,22107,22108,22109,22110,22111,22113,22114,22115,22116,22118,22119,22120,22121,22122,22123,22124,22125,22126,22127,22128,22129,22130,22131,22132,22133,22135,22136,22137,22139,22140,22141,22142,22143,22144,22145,22146,22147,22148,22149,22150,22151,22168,22170,22171,22172,22173,22175,22176,22177,22178,22179,22180,22181,22182,22184,22185,22189,22190,22191,22193,22195,22197,22222,22501,22502,22503,22801,22802)</LimitationValue>
    <LimitationType>2</LimitationType>
    <ActionType>1</ActionType>
    <LimitationName />
    <Code1>175</Code1>
    <Code2>4897</Code2>
    <Code3>135</Code3>
    <StartDatetime>1900-01-01T00:00:00+06:00</StartDatetime>
    <StopDatetime>9999-12-31T00:00:00+07:00</StopDatetime>
  </Limitation>
  <Limitation>
    <LimitationKey>61508</LimitationKey>
    <LimitationObjectType>11</LimitationObjectType>
    <LimitationObjectKey>426791</LimitationObjectKey>
    <LimitationValue>(22103,22104,22105,22107,22108,22109,22110,22111,22113,22114,22115,22116,22118,22119,22120,22121,22122,22123,22124,22125,22126,22127,22128,22129,22130,22131,22132,22133,22135,22136,22137,22139,22140,22141,22142,22143,22144,22145,22146,22147,22148,22149,22150,22151,22168,22170,22171,22172,22173,22175,22176,22177,22178,22179,22180,22181,22182,22184,22185,22189,22190,22191,22193,22195,22197,22222,22501,22502,22503,22801,22802)</LimitationValue>
    <LimitationType>2</LimitationType>
    <ActionType>1</ActionType>
    <LimitationName />
    <Code1>175</Code1>
    <Code2>4897</Code2>
    <Code3>136</Code3>
    <StartDatetime>1900-01-01T00:00:00+06:00</StartDatetime>
    <StopDatetime>9999-12-31T00:00:00+07:00</StopDatetime>
  </Limitation>
  <Limitation>
    <LimitationKey>61497</LimitationKey>
    <LimitationObjectType>3</LimitationObjectType>
    <LimitationObjectKey>4967</LimitationObjectKey>
    <LimitationValue>(42029)</LimitationValue>
    <LimitationType>2</LimitationType>
    <ActionType>1</ActionType>
    <LimitationName />
    <Code1>175</Code1>
    <Code2>4965</Code2>
    <Code3>0</Code3>
    <StartDatetime>1900-01-01T00:00:00+06:00</StartDatetime>
    <StopDatetime>9999-12-31T00:00:00+07:00</StopDatetime>
  </Limitation>
  <Limitation>
    <LimitationKey>61504</LimitationKey>
    <LimitationObjectType>11</LimitationObjectType>
    <LimitationObjectKey>426787</LimitationObjectKey>
    <LimitationValue>(22103,22104,22105,22107,22108,22109,22110,22111,22113,22114,22115,22116,22118,22119,22120,22121,22122,22123,22124,22125,22126,22127,22128,22129,22130,22131,22132,22133,22135,22136,22137,22139,22140,22141,22142,22143,22144,22145,22146,22147,22148,22149,22150,22151,22168,22170,22171,22172,22173,22175,22176,22177,22178,22179,22180,22181,22182,22184,22185,22189,22190,22191,22193,22195,22197,22222,22501,22502,22503,22801,22802)</LimitationValue>
    <LimitationType>2</LimitationType>
    <ActionType>1</ActionType>
    <LimitationName />
    <Code1>175</Code1>
    <Code2>4897</Code2>
    <Code3>132</Code3>
    <StartDatetime>1900-01-01T00:00:00+06:00</StartDatetime>
    <StopDatetime>9999-12-31T00:00:00+07:00</StopDatetime>
  </Limitation>
  <Limitation>
    <LimitationKey>61505</LimitationKey>
    <LimitationObjectType>11</LimitationObjectType>
    <LimitationObjectKey>426788</LimitationObjectKey>
    <LimitationValue>(22103,22104,22105,22107,22108,22109,22110,22111,22113,22114,22115,22116,22118,22119,22120,22121,22122,22123,22124,22125,22126,22127,22128,22129,22130,22131,22132,22133,22135,22136,22137,22139,22140,22141,22142,22143,22144,22145,22146,22147,22148,22149,22150,22151,22168,22170,22171,22172,22173,22175,22176,22177,22178,22179,22180,22181,22182,22184,22185,22189,22190,22191,22193,22195,22197,22222,22501,22502,22503,22801,22802)</LimitationValue>
    <LimitationType>2</LimitationType>
    <ActionType>1</ActionType>
    <LimitationName />
    <Code1>175</Code1>
    <Code2>4897</Code2>
    <Code3>133</Code3>
    <StartDatetime>1900-01-01T00:00:00+06:00</StartDatetime>
    <StopDatetime>9999-12-31T00:00:00+07:00</StopDatetime>
  </Limitation>
  <Limitation>
    <LimitationKey>61506</LimitationKey>
    <LimitationObjectType>11</LimitationObjectType>
    <LimitationObjectKey>426789</LimitationObjectKey>
    <LimitationValue>(22103,22104,22105,22107,22108,22109,22110,22111,22113,22114,22115,22116,22118,22119,22120,22121,22122,22123,22124,22125,22126,22127,22128,22129,22130,22131,22132,22133,22135,22136,22137,22139,22140,22141,22142,22143,22144,22145,22146,22147,22148,22149,22150,22151,22168,22170,22171,22172,22173,22175,22176,22177,22178,22179,22180,22181,22182,22184,22185,22189,22190,22191,22193,22195,22197,22222,22501,22502,22503,22801,22802)</LimitationValue>
    <LimitationType>2</LimitationType>
    <ActionType>1</ActionType>
    <LimitationName />
    <Code1>175</Code1>
    <Code2>4897</Code2>
    <Code3>134</Code3>
    <StartDatetime>1900-01-01T00:00:00+06:00</StartDatetime>
    <StopDatetime>9999-12-31T00:00:00+07:00</StopDatetime>
  </Limitation>
  <Limitation>
    <LimitationKey>61515</LimitationKey>
    <LimitationObjectType>11</LimitationObjectType>
    <LimitationObjectKey>426798</LimitationObjectKey>
    <LimitationValue>(22103,22104,22105,22107,22108,22109,22110,22111,22113,22114,22115,22116,22118,22119,22120,22121,22122,22123,22124,22125,22126,22127,22128,22129,22130,22131,22132,22133,22135,22136,22137,22139,22140,22141,22142,22143,22144,22145,22146,22147,22148,22149,22150,22151,22168,22170,22171,22172,22173,22175,22176,22177,22178,22179,22180,22181,22182,22184,22185,22189,22190,22191,22193,22195,22197,22222,22501,22502,22503,22801,22802)</LimitationValue>
    <LimitationType>2</LimitationType>
    <ActionType>1</ActionType>
    <LimitationName />
    <Code1>175</Code1>
    <Code2>4897</Code2>
    <Code3>143</Code3>
    <StartDatetime>1900-01-01T00:00:00+06:00</StartDatetime>
    <StopDatetime>9999-12-31T00:00:00+07:00</StopDatetime>
  </Limitation>
  <Limitation>
    <LimitationKey>61516</LimitationKey>
    <LimitationObjectType>11</LimitationObjectType>
    <LimitationObjectKey>426799</LimitationObjectKey>
    <LimitationValue>(22103,22104,22105,22107,22108,22109,22110,22111,22113,22114,22115,22116,22118,22119,22120,22121,22122,22123,22124,22125,22126,22127,22128,22129,22130,22131,22132,22133,22135,22136,22137,22139,22140,22141,22142,22143,22144,22145,22146,22147,22148,22149,22150,22151,22168,22170,22171,22172,22173,22175,22176,22177,22178,22179,22180,22181,22182,22184,22185,22189,22190,22191,22193,22195,22197,22222,22501,22502,22503,22801,22802)</LimitationValue>
    <LimitationType>2</LimitationType>
    <ActionType>1</ActionType>
    <LimitationName />
    <Code1>175</Code1>
    <Code2>4897</Code2>
    <Code3>144</Code3>
    <StartDatetime>1900-01-01T00:00:00+06:00</StartDatetime>
    <StopDatetime>9999-12-31T00:00:00+07:00</StopDatetime>
  </Limitation>
  <Limitation>
    <LimitationKey>61517</LimitationKey>
    <LimitationObjectType>11</LimitationObjectType>
    <LimitationObjectKey>426800</LimitationObjectKey>
    <LimitationValue>(22103,22104,22105,22107,22108,22109,22110,22111,22113,22114,22115,22116,22118,22119,22120,22121,22122,22123,22124,22125,22126,22127,22128,22129,22130,22131,22132,22133,22135,22136,22137,22139,22140,22141,22142,22143,22144,22145,22146,22147,22148,22149,22150,22151,22168,22170,22171,22172,22173,22175,22176,22177,22178,22179,22180,22181,22182,22184,22185,22189,22190,22191,22193,22195,22197,22222,22501,22502,22503,22801,22802)</LimitationValue>
    <LimitationType>2</LimitationType>
    <ActionType>1</ActionType>
    <LimitationName />
    <Code1>175</Code1>
    <Code2>4897</Code2>
    <Code3>145</Code3>
    <StartDatetime>1900-01-01T00:00:00+06:00</StartDatetime>
    <StopDatetime>9999-12-31T00:00:00+07:00</StopDatetime>
  </Limitation>
  <Limitation>
    <LimitationKey>61518</LimitationKey>
    <LimitationObjectType>11</LimitationObjectType>
    <LimitationObjectKey>426801</LimitationObjectKey>
    <LimitationValue>(22103,22104,22105,22107,22108,22109,22110,22111,22113,22114,22115,22116,22118,22119,22120,22121,22122,22123,22124,22125,22126,22127,22128,22129,22130,22131,22132,22133,22135,22136,22137,22139,22140,22141,22142,22143,22144,22145,22146,22147,22148,22149,22150,22151,22168,22170,22171,22172,22173,22175,22176,22177,22178,22179,22180,22181,22182,22184,22185,22189,22190,22191,22193,22195,22197,22222,22501,22502,22503,22801,22802)</LimitationValue>
    <LimitationType>2</LimitationType>
    <ActionType>1</ActionType>
    <LimitationName />
    <Code1>175</Code1>
    <Code2>4897</Code2>
    <Code3>146</Code3>
    <StartDatetime>1900-01-01T00:00:00+06:00</StartDatetime>
    <StopDatetime>9999-12-31T00:00:00+07:00</StopDatetime>
  </Limitation>
  <Limitation>
    <LimitationKey>61519</LimitationKey>
    <LimitationObjectType>11</LimitationObjectType>
    <LimitationObjectKey>426802</LimitationObjectKey>
    <LimitationValue>(22103,22104,22105,22107,22108,22109,22110,22111,22113,22114,22115,22116,22118,22119,22120,22121,22122,22123,22124,22125,22126,22127,22128,22129,22130,22131,22132,22133,22135,22136,22137,22139,22140,22141,22142,22143,22144,22145,22146,22147,22148,22149,22150,22151,22168,22170,22171,22172,22173,22175,22176,22177,22178,22179,22180,22181,22182,22184,22185,22189,22190,22191,22193,22195,22197,22222,22501,22502,22503,22801,22802)</LimitationValue>
    <LimitationType>2</LimitationType>
    <ActionType>1</ActionType>
    <LimitationName />
    <Code1>175</Code1>
    <Code2>4897</Code2>
    <Code3>147</Code3>
    <StartDatetime>1900-01-01T00:00:00+06:00</StartDatetime>
    <StopDatetime>9999-12-31T00:00:00+07:00</StopDatetime>
  </Limitation>
  <Limitation>
    <LimitationKey>61520</LimitationKey>
    <LimitationObjectType>11</LimitationObjectType>
    <LimitationObjectKey>426803</LimitationObjectKey>
    <LimitationValue>(22103,22104,22105,22107,22108,22109,22110,22111,22113,22114,22115,22116,22118,22119,22120,22121,22122,22123,22124,22125,22126,22127,22128,22129,22130,22131,22132,22133,22135,22136,22137,22139,22140,22141,22142,22143,22144,22145,22146,22147,22148,22149,22150,22151,22168,22170,22171,22172,22173,22175,22176,22177,22178,22179,22180,22181,22182,22184,22185,22189,22190,22191,22193,22195,22197,22222,22501,22502,22503,22801,22802)</LimitationValue>
    <LimitationType>2</LimitationType>
    <ActionType>1</ActionType>
    <LimitationName />
    <Code1>175</Code1>
    <Code2>4897</Code2>
    <Code3>148</Code3>
    <StartDatetime>1900-01-01T00:00:00+06:00</StartDatetime>
    <StopDatetime>9999-12-31T00:00:00+07:00</StopDatetime>
  </Limitation>
  <Limitation>
    <LimitationKey>61521</LimitationKey>
    <LimitationObjectType>11</LimitationObjectType>
    <LimitationObjectKey>426804</LimitationObjectKey>
    <LimitationValue>(22103,22104,22105,22107,22108,22109,22110,22111,22113,22114,22115,22116,22118,22119,22120,22121,22122,22123,22124,22125,22126,22127,22128,22129,22130,22131,22132,22133,22135,22136,22137,22139,22140,22141,22142,22143,22144,22145,22146,22147,22148,22149,22150,22151,22168,22170,22171,22172,22173,22175,22176,22177,22178,22179,22180,22181,22182,22184,22185,22189,22190,22191,22193,22195,22197,22222,22501,22502,22503,22801,22802)</LimitationValue>
    <LimitationType>2</LimitationType>
    <ActionType>1</ActionType>
    <LimitationName />
    <Code1>175</Code1>
    <Code2>4897</Code2>
    <Code3>149</Code3>
    <StartDatetime>1900-01-01T00:00:00+06:00</StartDatetime>
    <StopDatetime>9999-12-31T00:00:00+07:00</StopDatetime>
  </Limitation>
  <Limitation>
    <LimitationKey>61522</LimitationKey>
    <LimitationObjectType>11</LimitationObjectType>
    <LimitationObjectKey>426805</LimitationObjectKey>
    <LimitationValue>(22103,22104,22105,22107,22108,22109,22110,22111,22113,22114,22115,22116,22118,22119,22120,22121,22122,22123,22124,22125,22126,22127,22128,22129,22130,22131,22132,22133,22135,22136,22137,22139,22140,22141,22142,22143,22144,22145,22146,22147,22148,22149,22150,22151,22168,22170,22171,22172,22173,22175,22176,22177,22178,22179,22180,22181,22182,22184,22185,22189,22190,22191,22193,22195,22197,22222,22501,22502,22503,22801,22802)</LimitationValue>
    <LimitationType>2</LimitationType>
    <ActionType>1</ActionType>
    <LimitationName />
    <Code1>175</Code1>
    <Code2>4897</Code2>
    <Code3>150</Code3>
    <StartDatetime>1900-01-01T00:00:00+06:00</StartDatetime>
    <StopDatetime>9999-12-31T00:00:00+07:00</StopDatetime>
  </Limitation>
  <Limitation>
    <LimitationKey>61523</LimitationKey>
    <LimitationObjectType>11</LimitationObjectType>
    <LimitationObjectKey>426806</LimitationObjectKey>
    <LimitationValue>(22103,22104,22105,22107,22108,22109,22110,22111,22113,22114,22115,22116,22118,22119,22120,22121,22122,22123,22124,22125,22126,22127,22128,22129,22130,22131,22132,22133,22135,22136,22137,22139,22140,22141,22142,22143,22144,22145,22146,22147,22148,22149,22150,22151,22168,22170,22171,22172,22173,22175,22176,22177,22178,22179,22180,22181,22182,22184,22185,22189,22190,22191,22193,22195,22197,22222,22501,22502,22503,22801,22802)</LimitationValue>
    <LimitationType>2</LimitationType>
    <ActionType>1</ActionType>
    <LimitationName />
    <Code1>175</Code1>
    <Code2>4897</Code2>
    <Code3>151</Code3>
    <StartDatetime>1900-01-01T00:00:00+06:00</StartDatetime>
    <StopDatetime>9999-12-31T00:00:00+07:00</StopDatetime>
  </Limitation>
  <Limitation>
    <LimitationKey>61524</LimitationKey>
    <LimitationObjectType>11</LimitationObjectType>
    <LimitationObjectKey>426808</LimitationObjectKey>
    <LimitationValue>(22103,22104,22105,22107,22108,22109,22110,22111,22113,22114,22115,22116,22118,22119,22120,22121,22122,22123,22124,22125,22126,22127,22128,22129,22130,22131,22132,22133,22135,22136,22137,22139,22140,22141,22142,22143,22144,22145,22146,22147,22148,22149,22150,22151,22168,22170,22171,22172,22173,22175,22176,22177,22178,22179,22180,22181,22182,22184,22185,22189,22190,22191,22193,22195,22197,22222,22501,22502,22503,22801,22802)</LimitationValue>
    <LimitationType>2</LimitationType>
    <ActionType>1</ActionType>
    <LimitationName />
    <Code1>175</Code1>
    <Code2>4897</Code2>
    <Code3>152</Code3>
    <StartDatetime>1900-01-01T00:00:00+06:00</StartDatetime>
    <StopDatetime>9999-12-31T00:00:00+07:00</StopDatetime>
  </Limitation>
  <Limitation>
    <LimitationKey>61525</LimitationKey>
    <LimitationObjectType>11</LimitationObjectType>
    <LimitationObjectKey>426809</LimitationObjectKey>
    <LimitationValue>(22103,22104,22105,22107,22108,22109,22110,22111,22113,22114,22115,22116,22118,22119,22120,22121,22122,22123,22124,22125,22126,22127,22128,22129,22130,22131,22132,22133,22135,22136,22137,22139,22140,22141,22142,22143,22144,22145,22146,22147,22148,22149,22150,22151,22168,22170,22171,22172,22173,22175,22176,22177,22178,22179,22180,22181,22182,22184,22185,22189,22190,22191,22193,22195,22197,22222,22501,22502,22503,22801,22802)</LimitationValue>
    <LimitationType>2</LimitationType>
    <ActionType>1</ActionType>
    <LimitationName />
    <Code1>175</Code1>
    <Code2>4897</Code2>
    <Code3>153</Code3>
    <StartDatetime>1900-01-01T00:00:00+06:00</StartDatetime>
    <StopDatetime>9999-12-31T00:00:00+07:00</StopDatetime>
  </Limitation>
  <Limitation>
    <LimitationKey>61976</LimitationKey>
    <LimitationObjectType>3</LimitationObjectType>
    <LimitationObjectKey>4976</LimitationObjectKey>
    <LimitationValue>(54040)</LimitationValue>
    <LimitationType>2</LimitationType>
    <ActionType>1</ActionType>
    <LimitationName />
    <Code1>175</Code1>
    <Code2>4974</Code2>
    <Code3>0</Code3>
    <StartDatetime>1900-01-01T00:00:00+06:00</StartDatetime>
    <StopDatetime>9999-12-31T00:00:00+07:00</StopDatetime>
  </Limitation>
  <Limitation>
    <LimitationKey>61977</LimitationKey>
    <LimitationObjectType>11</LimitationObjectType>
    <LimitationObjectKey>427315</LimitationObjectKey>
    <LimitationValue>(54040)</LimitationValue>
    <LimitationType>2</LimitationType>
    <ActionType>1</ActionType>
    <LimitationName />
    <Code1>175</Code1>
    <Code2>4974</Code2>
    <Code3>1</Code3>
    <StartDatetime>1900-01-01T00:00:00+06:00</StartDatetime>
    <StopDatetime>9999-12-31T00:00:00+07:00</StopDatetime>
  </Limitation>
  <Limitation>
    <LimitationKey>62073</LimitationKey>
    <LimitationObjectType>3</LimitationObjectType>
    <LimitationObjectKey>4989</LimitationObjectKey>
    <LimitationValue>(22184)</LimitationValue>
    <LimitationType>2</LimitationType>
    <ActionType>1</ActionType>
    <LimitationName />
    <Code1>175</Code1>
    <Code2>0</Code2>
    <Code3>0</Code3>
    <StartDatetime>1900-01-01T00:00:00+06:00</StartDatetime>
    <StopDatetime>9999-12-31T00:00:00+07:00</StopDatetime>
  </Limitation>
  <Limitation>
    <LimitationKey>62092</LimitationKey>
    <LimitationObjectType>3</LimitationObjectType>
    <LimitationObjectKey>4992</LimitationObjectKey>
    <LimitationValue>(42164)</LimitationValue>
    <LimitationType>2</LimitationType>
    <ActionType>1</ActionType>
    <LimitationName />
    <Code1>175</Code1>
    <Code2>4989</Code2>
    <Code3>0</Code3>
    <StartDatetime>1900-01-01T00:00:00+06:00</StartDatetime>
    <StopDatetime>9999-12-31T00:00:00+07:00</StopDatetime>
  </Limitation>
  <Limitation>
    <LimitationKey>62087</LimitationKey>
    <LimitationObjectType>3</LimitationObjectType>
    <LimitationObjectKey>4991</LimitationObjectKey>
    <LimitationValue>(42166)</LimitationValue>
    <LimitationType>2</LimitationType>
    <ActionType>1</ActionType>
    <LimitationName />
    <Code1>175</Code1>
    <Code2>4988</Code2>
    <Code3>0</Code3>
    <StartDatetime>1900-01-01T00:00:00+06:00</StartDatetime>
    <StopDatetime>9999-12-31T00:00:00+07:00</StopDatetime>
  </Limitation>
  <Limitation>
    <LimitationKey>62142</LimitationKey>
    <LimitationObjectType>3</LimitationObjectType>
    <LimitationObjectKey>5001</LimitationObjectKey>
    <LimitationValue>(22103,22104,22105,22107,22108,22109,22110,22111,22113,22114,22115,22116,22118,22119,22120,22121,22122,22123,22124,22125,22126,22127,22128,22129,22130,22131,22132,22133,22135,22136,22137,22139,22140,22141,22142,22143,22144,22145,22146,22147,22148,22149,22150,22151,22168,22170,22171,22172,22173,22175,22176,22177,22178,22179,22180,22181,22182,22184,22185,22189,22190,22191,22193,22195,22197,22501,22502,22503,22801,22802)</LimitationValue>
    <LimitationType>2</LimitationType>
    <ActionType>1</ActionType>
    <LimitationName />
    <Code1>175</Code1>
    <Code2>4998</Code2>
    <Code3>0</Code3>
    <StartDatetime>1900-01-01T00:00:00+06:00</StartDatetime>
    <StopDatetime>9999-12-31T00:00:00+07:00</StopDatetime>
  </Limitation>
  <Limitation>
    <LimitationKey>62143</LimitationKey>
    <LimitationObjectType>3</LimitationObjectType>
    <LimitationObjectKey>5000</LimitationObjectKey>
    <LimitationValue>(22103,22104,22105,22107,22108,22109,22110,22111,22113,22114,22115,22116,22118,22119,22120,22121,22122,22123,22124,22125,22126,22127,22128,22129,22130,22131,22132,22133,22135,22136,22137,22139,22140,22141,22142,22143,22144,22145,22146,22147,22148,22149,22150,22151,22168,22170,22171,22172,22173,22175,22176,22177,22178,22179,22180,22181,22182,22184,22185,22189,22190,22191,22193,22195,22197,22501,22502,22503,22801,22802)</LimitationValue>
    <LimitationType>2</LimitationType>
    <ActionType>1</ActionType>
    <LimitationName />
    <Code1>175</Code1>
    <Code2>4997</Code2>
    <Code3>0</Code3>
    <StartDatetime>1900-01-01T00:00:00+06:00</StartDatetime>
    <StopDatetime>9999-12-31T00:00:00+07:00</StopDatetime>
  </Limitation>
  <Limitation>
    <LimitationKey>62144</LimitationKey>
    <LimitationObjectType>3</LimitationObjectType>
    <LimitationObjectKey>4999</LimitationObjectKey>
    <LimitationValue>(22103,22104,22105,22107,22108,22109,22110,22111,22113,22114,22115,22116,22118,22119,22120,22121,22122,22123,22124,22125,22126,22127,22128,22129,22130,22131,22132,22133,22135,22136,22137,22139,22140,22141,22142,22143,22144,22145,22146,22147,22148,22149,22150,22151,22168,22170,22171,22172,22173,22175,22176,22177,22178,22179,22180,22181,22182,22184,22185,22189,22190,22191,22193,22195,22197,22501,22502,22503,22801,22802)</LimitationValue>
    <LimitationType>2</LimitationType>
    <ActionType>1</ActionType>
    <LimitationName />
    <Code1>175</Code1>
    <Code2>4996</Code2>
    <Code3>0</Code3>
    <StartDatetime>1900-01-01T00:00:00+06:00</StartDatetime>
    <StopDatetime>9999-12-31T00:00:00+07:00</StopDatetime>
  </Limitation>
  <Limitation>
    <LimitationKey>62205</LimitationKey>
    <LimitationObjectType>3</LimitationObjectType>
    <LimitationObjectKey>5003</LimitationObjectKey>
    <LimitationValue>(54086)</LimitationValue>
    <LimitationType>2</LimitationType>
    <ActionType>1</ActionType>
    <LimitationName />
    <Code1>175</Code1>
    <Code2>5000</Code2>
    <Code3>0</Code3>
    <StartDatetime>1900-01-01T00:00:00+06:00</StartDatetime>
    <StopDatetime>9999-12-31T00:00:00+07:00</StopDatetime>
  </Limitation>
  <Limitation>
    <LimitationKey>62257</LimitationKey>
    <LimitationObjectType>3</LimitationObjectType>
    <LimitationObjectKey>5011</LimitationObjectKey>
    <LimitationValue>(22103,22104,22105,22107,22108,22109,22110,22111,22113,22114,22115,22116,22118,22119,22120,22121,22122,22123,22124,22125,22126,22127,22128,22129,22130,22131,22132,22133,22135,22136,22137,22139,22140,22141,22142,22143,22144,22145,22146,22147,22148,22149,22150,22151,22168,22170,22171,22172,22173,22175,22176,22177,22178,22179,22180,22181,22182,22184,22185,22189,22190,22191,22193,22195,22197,22501,22502,22503,22801,22802)</LimitationValue>
    <LimitationType>2</LimitationType>
    <ActionType>1</ActionType>
    <LimitationName />
    <Code1>175</Code1>
    <Code2>5008</Code2>
    <Code3>0</Code3>
    <StartDatetime>1900-01-01T00:00:00+06:00</StartDatetime>
    <StopDatetime>9999-12-31T00:00:00+07:00</StopDatetime>
  </Limitation>
  <Limitation>
    <LimitationKey>62282</LimitationKey>
    <LimitationObjectType>3</LimitationObjectType>
    <LimitationObjectKey>5016</LimitationObjectKey>
    <LimitationValue>(22109)</LimitationValue>
    <LimitationType>2</LimitationType>
    <ActionType>1</ActionType>
    <LimitationName />
    <Code1>175</Code1>
    <Code2>5013</Code2>
    <Code3>0</Code3>
    <StartDatetime>1900-01-01T00:00:00+06:00</StartDatetime>
    <StopDatetime>9999-12-31T00:00:00+07:00</StopDatetime>
  </Limitation>
  <Limitation>
    <LimitationKey>229479</LimitationKey>
    <LimitationObjectType>11</LimitationObjectType>
    <LimitationObjectKey>436039</LimitationObjectKey>
    <LimitationValue>(22170,22179,22180,22181,22191,22193,22502,22801,22802)</LimitationValue>
    <LimitationType>2</LimitationType>
    <ActionType>2</ActionType>
    <LimitationName />
    <Code1>175</Code1>
    <Code2>4898</Code2>
    <Code3>334</Code3>
    <StartDatetime>1900-01-01T00:00:00+06:00</StartDatetime>
    <StopDatetime>9999-12-31T00:00:00+07:00</StopDatetime>
  </Limitation>
  <Limitation>
    <LimitationKey>225555</LimitationKey>
    <LimitationObjectType>11</LimitationObjectType>
    <LimitationObjectKey>430336</LimitationObjectKey>
    <LimitationValue>(22180,22181,22191,22193,22197,22502,22801,22802)</LimitationValue>
    <LimitationType>2</LimitationType>
    <ActionType>1</ActionType>
    <LimitationName />
    <Code1>175</Code1>
    <Code2>0</Code2>
    <Code3>0</Code3>
    <StartDatetime>1900-01-01T00:00:00+06:00</StartDatetime>
    <StopDatetime>9999-12-31T00:00:00+07:00</StopDatetime>
  </Limitation>
  <Limitation>
    <LimitationKey>225559</LimitationKey>
    <LimitationObjectType>3</LimitationObjectType>
    <LimitationObjectKey>6581</LimitationObjectKey>
    <LimitationValue>(42016,42018,42022,42027,42029,42030,42032,42152,42153,42155,42157,42158,42159,42160)</LimitationValue>
    <LimitationType>2</LimitationType>
    <ActionType>1</ActionType>
    <LimitationName />
    <Code1>175</Code1>
    <Code2>6578</Code2>
    <Code3>0</Code3>
    <StartDatetime>1900-01-01T00:00:00+06:00</StartDatetime>
    <StopDatetime>9999-12-31T00:00:00+07:00</StopDatetime>
  </Limitation>
  <Limitation>
    <LimitationKey>225696</LimitationKey>
    <LimitationObjectType>11</LimitationObjectType>
    <LimitationObjectKey>430829</LimitationObjectKey>
    <LimitationValue>(22179,22180,22181,22191,22193,22197,22502,22801,22802)</LimitationValue>
    <LimitationType>2</LimitationType>
    <ActionType>1</ActionType>
    <LimitationName />
    <Code1>175</Code1>
    <Code2>876</Code2>
    <Code3>50</Code3>
    <StartDatetime>1900-01-01T00:00:00+06:00</StartDatetime>
    <StopDatetime>9999-12-31T00:00:00+07:00</StopDatetime>
  </Limitation>
  <Limitation>
    <LimitationKey>225761</LimitationKey>
    <LimitationObjectType>3</LimitationObjectType>
    <LimitationObjectKey>6624</LimitationObjectKey>
    <LimitationValue>(22168)</LimitationValue>
    <LimitationType>2</LimitationType>
    <ActionType>1</ActionType>
    <LimitationName />
    <Code1>175</Code1>
    <Code2>6621</Code2>
    <Code3>0</Code3>
    <StartDatetime>1900-01-01T00:00:00+06:00</StartDatetime>
    <StopDatetime>9999-12-31T00:00:00+07:00</StopDatetime>
  </Limitation>
  <Limitation>
    <LimitationKey>230664</LimitationKey>
    <LimitationObjectType>3</LimitationObjectType>
    <LimitationObjectKey>4906</LimitationObjectKey>
    <LimitationValue>(19208,19212,19213)</LimitationValue>
    <LimitationType>2</LimitationType>
    <ActionType>1</ActionType>
    <LimitationName />
    <Code1>175</Code1>
    <Code2>4904</Code2>
    <Code3>0</Code3>
    <StartDatetime>1900-01-01T00:00:00+06:00</StartDatetime>
    <StopDatetime>9999-12-31T00:00:00+07:00</StopDatetime>
  </Limitation>
  <Limitation>
    <LimitationKey>228589</LimitationKey>
    <LimitationObjectType>3</LimitationObjectType>
    <LimitationObjectKey>6683</LimitationObjectKey>
    <LimitationValue>(42020)</LimitationValue>
    <LimitationType>2</LimitationType>
    <ActionType>1</ActionType>
    <LimitationName />
    <Code1>175</Code1>
    <Code2>6680</Code2>
    <Code3>0</Code3>
    <StartDatetime>1900-01-01T00:00:00+06:00</StartDatetime>
    <StopDatetime>9999-12-31T00:00:00+07:00</StopDatetime>
  </Limitation>
  <Limitation>
    <LimitationKey>228592</LimitationKey>
    <LimitationObjectType>3</LimitationObjectType>
    <LimitationObjectKey>6684</LimitationObjectKey>
    <LimitationValue>(42014)</LimitationValue>
    <LimitationType>2</LimitationType>
    <ActionType>1</ActionType>
    <LimitationName />
    <Code1>175</Code1>
    <Code2>6681</Code2>
    <Code3>0</Code3>
    <StartDatetime>1900-01-01T00:00:00+06:00</StartDatetime>
    <StopDatetime>9999-12-31T00:00:00+07:00</StopDatetime>
  </Limitation>
  <Limitation>
    <LimitationKey>228613</LimitationKey>
    <LimitationObjectType>3</LimitationObjectType>
    <LimitationObjectKey>6685</LimitationObjectKey>
    <LimitationValue>(54088)</LimitationValue>
    <LimitationType>2</LimitationType>
    <ActionType>1</ActionType>
    <LimitationName />
    <Code1>175</Code1>
    <Code2>6682</Code2>
    <Code3>0</Code3>
    <StartDatetime>1900-01-01T00:00:00+06:00</StartDatetime>
    <StopDatetime>9999-12-31T00:00:00+07:00</StopDatetime>
  </Limitation>
  <Limitation>
    <LimitationKey>228719</LimitationKey>
    <LimitationObjectType>11</LimitationObjectType>
    <LimitationObjectKey>439854</LimitationObjectKey>
    <LimitationValue>(54001,54002,54003,54004,54005,54006,54007,54008,54010,54011,54012,54013,54014,54015,54016,54017,54019,54020,54021,54022,54024,54025,54026,54027,54028,54029,54030,54031,54032,54034,54035,54036,54037,54038,54039,54040,54041,54043,54044,54047,54050,54051,54052,54055,54056,54057,54058,54060,54061,54064,54066,54080,54081,54083,54084,54085,54086,54087,54088,54089,54090,54091,54092,54704,54715,54793,54901,54902,54903,54904,54905,54906,54907,54908,54909,54910,54911,54912,54913,54914,54915,54916,54917,54918)</LimitationValue>
    <LimitationType>2</LimitationType>
    <ActionType>1</ActionType>
    <LimitationName />
    <Code1>175</Code1>
    <Code2>4898</Code2>
    <Code3>384</Code3>
    <StartDatetime>1900-01-01T00:00:00+06:00</StartDatetime>
    <StopDatetime>9999-12-31T00:00:00+07:00</StopDatetime>
  </Limitation>
  <Limitation>
    <LimitationKey>228720</LimitationKey>
    <LimitationObjectType>11</LimitationObjectType>
    <LimitationObjectKey>441460</LimitationObjectKey>
    <LimitationValue>(776,777,22103,22104,22105,22107,22108,22109,22110,22111,22113,22114,22115,22116,22118,22119,22120,22121,22122,22123,22124,22125,22126,22127,22128,22129,22130,22131,22132,22133,22135,22136,22137,22139,22140,22141,22142,22143,22144,22145,22146,22147,22148,22149,22150,22151,22168,22170,22171,22172,22173,22175,22176,22177,22178,22179,22180,22181,22182,22184,22185,22189,22190,22191,22193,22195,22196,22197,22198,22222,22501,22502,22503,22801,22802,22806,22901,54001,54002,54003,54004,54005,54006,54007,54008,54010,54011,54012,54013,54014,54015,54016,54017,54019,54020,54021,54022,54024,54025,54026,54027,54028,54029,54030,54031,54032,54034,54035,54036,54037,54038,54039,54040,54041,54043,54044,54047,54050,54051,54052,54055,54056,54057,54058,54060,54061,54064,54066,54080,54081,54083,54084,54085,54086,54087,54088,54089,54090,54091,54092,54093,54704,54714,54715,54793,54794,54901,54902,54903,54904,54905,54906,54907,54908,54909,54910,54911,54912,54913,54914,54915,54916,54917,54918,54919,54920,55001,70901)</LimitationValue>
    <LimitationType>2</LimitationType>
    <ActionType>1</ActionType>
    <LimitationName />
    <Code1>175</Code1>
    <Code2>4898</Code2>
    <Code3>385</Code3>
    <StartDatetime>1900-01-01T00:00:00+06:00</StartDatetime>
    <StopDatetime>9999-12-31T00:00:00+07:00</StopDatetime>
  </Limitation>
  <Limitation>
    <LimitationKey>228740</LimitationKey>
    <LimitationObjectType>11</LimitationObjectType>
    <LimitationObjectKey>441689</LimitationObjectKey>
    <LimitationValue>(54001,54002,54003,54004,54005,54006,54007,54008,54010,54011,54012,54013,54014,54015,54016,54017,54019,54020,54021,54022,54024,54025,54026,54027,54028,54029,54030,54031,54032,54034,54035,54036,54037,54038,54039,54040,54041,54043,54044,54047,54050,54051,54052,54055,54056,54057,54058,54060,54061,54064,54066,54080,54081,54083,54084,54085,54086,54087,54088,54089,54090,54091,54092,54704,54715,54793,54901,54902,54903,54904,54905,54906,54907,54908,54909,54910,54911,54912,54913,54914,54915,54916,54917,54918)</LimitationValue>
    <LimitationType>2</LimitationType>
    <ActionType>1</ActionType>
    <LimitationName />
    <Code1>175</Code1>
    <Code2>0</Code2>
    <Code3>0</Code3>
    <StartDatetime>1900-01-01T00:00:00+06:00</StartDatetime>
    <StopDatetime>9999-12-31T00:00:00+07:00</StopDatetime>
  </Limitation>
  <Limitation>
    <LimitationKey>228741</LimitationKey>
    <LimitationObjectType>11</LimitationObjectType>
    <LimitationObjectKey>441690</LimitationObjectKey>
    <LimitationValue>(54001,54002,54003,54004,54005,54006,54007,54008,54010,54011,54012,54013,54014,54015,54016,54017,54019,54020,54021,54022,54024,54025,54026,54027,54028,54029,54030,54031,54032,54034,54035,54036,54037,54038,54039,54040,54041,54043,54044,54047,54050,54051,54052,54055,54056,54057,54058,54060,54061,54064,54066,54080,54081,54083,54084,54085,54086,54087,54088,54089,54090,54091,54092,54704,54715,54793,54901,54902,54903,54904,54905,54906,54907,54908,54909,54910,54911,54912,54913,54914,54915,54916,54917,54918)</LimitationValue>
    <LimitationType>2</LimitationType>
    <ActionType>1</ActionType>
    <LimitationName />
    <Code1>175</Code1>
    <Code2>0</Code2>
    <Code3>0</Code3>
    <StartDatetime>1900-01-01T00:00:00+06:00</StartDatetime>
    <StopDatetime>9999-12-31T00:00:00+07:00</StopDatetime>
  </Limitation>
  <Limitation>
    <LimitationKey>228742</LimitationKey>
    <LimitationObjectType>11</LimitationObjectType>
    <LimitationObjectKey>441691</LimitationObjectKey>
    <LimitationValue>(54001,54002,54003,54004,54005,54006,54007,54008,54010,54011,54012,54013,54014,54015,54016,54017,54019,54020,54021,54022,54024,54025,54026,54027,54028,54029,54030,54031,54032,54034,54035,54036,54037,54038,54039,54040,54041,54043,54044,54047,54050,54051,54052,54055,54056,54057,54058,54060,54061,54064,54066,54080,54081,54083,54084,54085,54086,54087,54088,54089,54090,54091,54092,54704,54715,54793,54901,54902,54903,54904,54905,54906,54907,54908,54909,54910,54911,54912,54913,54914,54915,54916,54917,54918)</LimitationValue>
    <LimitationType>2</LimitationType>
    <ActionType>1</ActionType>
    <LimitationName />
    <Code1>175</Code1>
    <Code2>0</Code2>
    <Code3>0</Code3>
    <StartDatetime>1900-01-01T00:00:00+06:00</StartDatetime>
    <StopDatetime>9999-12-31T00:00:00+07:00</StopDatetime>
  </Limitation>
  <Limitation>
    <LimitationKey>228743</LimitationKey>
    <LimitationObjectType>11</LimitationObjectType>
    <LimitationObjectKey>441692</LimitationObjectKey>
    <LimitationValue>(54001,54002,54003,54004,54005,54006,54007,54008,54010,54011,54012,54013,54014,54015,54016,54017,54019,54020,54021,54022,54024,54025,54026,54027,54028,54029,54030,54031,54032,54034,54035,54036,54037,54038,54039,54040,54041,54043,54044,54047,54050,54051,54052,54055,54056,54057,54058,54060,54061,54064,54066,54080,54081,54083,54084,54085,54086,54087,54088,54089,54090,54091,54092,54704,54715,54793,54901,54902,54903,54904,54905,54906,54907,54908,54909,54910,54911,54912,54913,54914,54915,54916,54917,54918)</LimitationValue>
    <LimitationType>2</LimitationType>
    <ActionType>1</ActionType>
    <LimitationName />
    <Code1>175</Code1>
    <Code2>0</Code2>
    <Code3>0</Code3>
    <StartDatetime>1900-01-01T00:00:00+06:00</StartDatetime>
    <StopDatetime>9999-12-31T00:00:00+07:00</StopDatetime>
  </Limitation>
  <Limitation>
    <LimitationKey>228744</LimitationKey>
    <LimitationObjectType>11</LimitationObjectType>
    <LimitationObjectKey>441693</LimitationObjectKey>
    <LimitationValue>(54001,54002,54003,54004,54005,54006,54007,54008,54010,54011,54012,54013,54014,54015,54016,54017,54019,54020,54021,54022,54024,54025,54026,54027,54028,54029,54030,54031,54032,54034,54035,54036,54037,54038,54039,54040,54041,54043,54044,54047,54050,54051,54052,54055,54056,54057,54058,54060,54061,54064,54066,54080,54081,54083,54084,54085,54086,54087,54088,54089,54090,54091,54092,54704,54715,54793,54901,54902,54903,54904,54905,54906,54907,54908,54909,54910,54911,54912,54913,54914,54915,54916,54917,54918)</LimitationValue>
    <LimitationType>2</LimitationType>
    <ActionType>1</ActionType>
    <LimitationName />
    <Code1>175</Code1>
    <Code2>0</Code2>
    <Code3>0</Code3>
    <StartDatetime>1900-01-01T00:00:00+06:00</StartDatetime>
    <StopDatetime>9999-12-31T00:00:00+07:00</StopDatetime>
  </Limitation>
  <Limitation>
    <LimitationKey>228745</LimitationKey>
    <LimitationObjectType>11</LimitationObjectType>
    <LimitationObjectKey>441694</LimitationObjectKey>
    <LimitationValue>(54001,54002,54003,54004,54005,54006,54007,54008,54010,54011,54012,54013,54014,54015,54016,54017,54019,54020,54021,54022,54024,54025,54026,54027,54028,54029,54030,54031,54032,54034,54035,54036,54037,54038,54039,54040,54041,54043,54044,54047,54050,54051,54052,54055,54056,54057,54058,54060,54061,54064,54066,54080,54081,54083,54084,54085,54086,54087,54088,54089,54090,54091,54092,54704,54715,54793,54901,54902,54903,54904,54905,54906,54907,54908,54909,54910,54911,54912,54913,54914,54915,54916,54917,54918)</LimitationValue>
    <LimitationType>2</LimitationType>
    <ActionType>1</ActionType>
    <LimitationName />
    <Code1>175</Code1>
    <Code2>0</Code2>
    <Code3>0</Code3>
    <StartDatetime>1900-01-01T00:00:00+06:00</StartDatetime>
    <StopDatetime>9999-12-31T00:00:00+07:00</StopDatetime>
  </Limitation>
  <Limitation>
    <LimitationKey>228746</LimitationKey>
    <LimitationObjectType>11</LimitationObjectType>
    <LimitationObjectKey>441695</LimitationObjectKey>
    <LimitationValue>(54001,54002,54003,54004,54005,54006,54007,54008,54010,54011,54012,54013,54014,54015,54016,54017,54019,54020,54021,54022,54024,54025,54026,54027,54028,54029,54030,54031,54032,54034,54035,54036,54037,54038,54039,54040,54041,54043,54044,54047,54050,54051,54052,54055,54056,54057,54058,54060,54061,54064,54066,54080,54081,54083,54084,54085,54086,54087,54088,54089,54090,54091,54092,54704,54715,54793,54901,54902,54903,54904,54905,54906,54907,54908,54909,54910,54911,54912,54913,54914,54915,54916,54917,54918)</LimitationValue>
    <LimitationType>2</LimitationType>
    <ActionType>1</ActionType>
    <LimitationName />
    <Code1>175</Code1>
    <Code2>0</Code2>
    <Code3>0</Code3>
    <StartDatetime>1900-01-01T00:00:00+06:00</StartDatetime>
    <StopDatetime>9999-12-31T00:00:00+07:00</StopDatetime>
  </Limitation>
  <Limitation>
    <LimitationKey>228747</LimitationKey>
    <LimitationObjectType>11</LimitationObjectType>
    <LimitationObjectKey>441696</LimitationObjectKey>
    <LimitationValue>(54001,54002,54003,54004,54005,54006,54007,54008,54010,54011,54012,54013,54014,54015,54016,54017,54019,54020,54021,54022,54024,54025,54026,54027,54028,54029,54030,54031,54032,54034,54035,54036,54037,54038,54039,54040,54041,54043,54044,54047,54050,54051,54052,54055,54056,54057,54058,54060,54061,54064,54066,54080,54081,54083,54084,54085,54086,54087,54088,54089,54090,54091,54092,54704,54715,54793,54901,54902,54903,54904,54905,54906,54907,54908,54909,54910,54911,54912,54913,54914,54915,54916,54917,54918)</LimitationValue>
    <LimitationType>2</LimitationType>
    <ActionType>1</ActionType>
    <LimitationName />
    <Code1>175</Code1>
    <Code2>0</Code2>
    <Code3>0</Code3>
    <StartDatetime>1900-01-01T00:00:00+06:00</StartDatetime>
    <StopDatetime>9999-12-31T00:00:00+07:00</StopDatetime>
  </Limitation>
  <Limitation>
    <LimitationKey>228748</LimitationKey>
    <LimitationObjectType>11</LimitationObjectType>
    <LimitationObjectKey>441697</LimitationObjectKey>
    <LimitationValue>(54001,54002,54003,54004,54005,54006,54007,54008,54010,54011,54012,54013,54014,54015,54016,54017,54019,54020,54021,54022,54024,54025,54026,54027,54028,54029,54030,54031,54032,54034,54035,54036,54037,54038,54039,54040,54041,54043,54044,54047,54050,54051,54052,54055,54056,54057,54058,54060,54061,54064,54066,54080,54081,54083,54084,54085,54086,54087,54088,54089,54090,54091,54092,54704,54715,54793,54901,54902,54903,54904,54905,54906,54907,54908,54909,54910,54911,54912,54913,54914,54915,54916,54917,54918)</LimitationValue>
    <LimitationType>2</LimitationType>
    <ActionType>1</ActionType>
    <LimitationName />
    <Code1>175</Code1>
    <Code2>0</Code2>
    <Code3>0</Code3>
    <StartDatetime>1900-01-01T00:00:00+06:00</StartDatetime>
    <StopDatetime>9999-12-31T00:00:00+07:00</StopDatetime>
  </Limitation>
  <Limitation>
    <LimitationKey>228749</LimitationKey>
    <LimitationObjectType>11</LimitationObjectType>
    <LimitationObjectKey>441698</LimitationObjectKey>
    <LimitationValue>(54001,54002,54003,54004,54005,54006,54007,54008,54010,54011,54012,54013,54014,54015,54016,54017,54019,54020,54021,54022,54024,54025,54026,54027,54028,54029,54030,54031,54032,54034,54035,54036,54037,54038,54039,54040,54041,54043,54044,54047,54050,54051,54052,54055,54056,54057,54058,54060,54061,54064,54066,54080,54081,54083,54084,54085,54086,54087,54088,54089,54090,54091,54092,54704,54715,54793,54901,54902,54903,54904,54905,54906,54907,54908,54909,54910,54911,54912,54913,54914,54915,54916,54917,54918)</LimitationValue>
    <LimitationType>2</LimitationType>
    <ActionType>1</ActionType>
    <LimitationName />
    <Code1>175</Code1>
    <Code2>0</Code2>
    <Code3>0</Code3>
    <StartDatetime>1900-01-01T00:00:00+06:00</StartDatetime>
    <StopDatetime>9999-12-31T00:00:00+07:00</StopDatetime>
  </Limitation>
  <Limitation>
    <LimitationKey>228750</LimitationKey>
    <LimitationObjectType>11</LimitationObjectType>
    <LimitationObjectKey>441699</LimitationObjectKey>
    <LimitationValue>(54001,54002,54003,54004,54005,54006,54007,54008,54010,54011,54012,54013,54014,54015,54016,54017,54019,54020,54021,54022,54024,54025,54026,54027,54028,54029,54030,54031,54032,54034,54035,54036,54037,54038,54039,54040,54041,54043,54044,54047,54050,54051,54052,54055,54056,54057,54058,54060,54061,54064,54066,54080,54081,54083,54084,54085,54086,54087,54088,54089,54090,54091,54092,54704,54715,54793,54901,54902,54903,54904,54905,54906,54907,54908,54909,54910,54911,54912,54913,54914,54915,54916,54917,54918)</LimitationValue>
    <LimitationType>2</LimitationType>
    <ActionType>1</ActionType>
    <LimitationName />
    <Code1>175</Code1>
    <Code2>0</Code2>
    <Code3>0</Code3>
    <StartDatetime>1900-01-01T00:00:00+06:00</StartDatetime>
    <StopDatetime>9999-12-31T00:00:00+07:00</StopDatetime>
  </Limitation>
  <Limitation>
    <LimitationKey>228751</LimitationKey>
    <LimitationObjectType>11</LimitationObjectType>
    <LimitationObjectKey>441700</LimitationObjectKey>
    <LimitationValue>(54001,54002,54003,54004,54005,54006,54007,54008,54010,54011,54012,54013,54014,54015,54016,54017,54019,54020,54021,54022,54024,54025,54026,54027,54028,54029,54030,54031,54032,54034,54035,54036,54037,54038,54039,54040,54041,54043,54044,54047,54050,54051,54052,54055,54056,54057,54058,54060,54061,54064,54066,54080,54081,54083,54084,54085,54086,54087,54088,54089,54090,54091,54092,54704,54715,54793,54901,54902,54903,54904,54905,54906,54907,54908,54909,54910,54911,54912,54913,54914,54915,54916,54917,54918)</LimitationValue>
    <LimitationType>2</LimitationType>
    <ActionType>1</ActionType>
    <LimitationName />
    <Code1>175</Code1>
    <Code2>0</Code2>
    <Code3>0</Code3>
    <StartDatetime>1900-01-01T00:00:00+06:00</StartDatetime>
    <StopDatetime>9999-12-31T00:00:00+07:00</StopDatetime>
  </Limitation>
  <Limitation>
    <LimitationKey>228752</LimitationKey>
    <LimitationObjectType>11</LimitationObjectType>
    <LimitationObjectKey>441701</LimitationObjectKey>
    <LimitationValue>(54001,54002,54003,54004,54005,54006,54007,54008,54010,54011,54012,54013,54014,54015,54016,54017,54019,54020,54021,54022,54024,54025,54026,54027,54028,54029,54030,54031,54032,54034,54035,54036,54037,54038,54039,54040,54041,54043,54044,54047,54050,54051,54052,54055,54056,54057,54058,54060,54061,54064,54066,54080,54081,54083,54084,54085,54086,54087,54088,54089,54090,54091,54092,54704,54715,54793,54901,54902,54903,54904,54905,54906,54907,54908,54909,54910,54911,54912,54913,54914,54915,54916,54917,54918)</LimitationValue>
    <LimitationType>2</LimitationType>
    <ActionType>1</ActionType>
    <LimitationName />
    <Code1>175</Code1>
    <Code2>0</Code2>
    <Code3>0</Code3>
    <StartDatetime>1900-01-01T00:00:00+06:00</StartDatetime>
    <StopDatetime>9999-12-31T00:00:00+07:00</StopDatetime>
  </Limitation>
  <Limitation>
    <LimitationKey>228753</LimitationKey>
    <LimitationObjectType>11</LimitationObjectType>
    <LimitationObjectKey>441702</LimitationObjectKey>
    <LimitationValue>(54001,54002,54003,54004,54005,54006,54007,54008,54010,54011,54012,54013,54014,54015,54016,54017,54019,54020,54021,54022,54024,54025,54026,54027,54028,54029,54030,54031,54032,54034,54035,54036,54037,54038,54039,54040,54041,54043,54044,54047,54050,54051,54052,54055,54056,54057,54058,54060,54061,54064,54066,54080,54081,54083,54084,54085,54086,54087,54088,54089,54090,54091,54092,54704,54715,54793,54901,54902,54903,54904,54905,54906,54907,54908,54909,54910,54911,54912,54913,54914,54915,54916,54917,54918)</LimitationValue>
    <LimitationType>2</LimitationType>
    <ActionType>1</ActionType>
    <LimitationName />
    <Code1>175</Code1>
    <Code2>0</Code2>
    <Code3>0</Code3>
    <StartDatetime>1900-01-01T00:00:00+06:00</StartDatetime>
    <StopDatetime>9999-12-31T00:00:00+07:00</StopDatetime>
  </Limitation>
  <Limitation>
    <LimitationKey>228754</LimitationKey>
    <LimitationObjectType>11</LimitationObjectType>
    <LimitationObjectKey>441703</LimitationObjectKey>
    <LimitationValue>(54001,54002,54003,54004,54005,54006,54007,54008,54010,54011,54012,54013,54014,54015,54016,54017,54019,54020,54021,54022,54024,54025,54026,54027,54028,54029,54030,54031,54032,54034,54035,54036,54037,54038,54039,54040,54041,54043,54044,54047,54050,54051,54052,54055,54056,54057,54058,54060,54061,54064,54066,54080,54081,54083,54084,54085,54086,54087,54088,54089,54090,54091,54092,54704,54715,54793,54901,54902,54903,54904,54905,54906,54907,54908,54909,54910,54911,54912,54913,54914,54915,54916,54917,54918)</LimitationValue>
    <LimitationType>2</LimitationType>
    <ActionType>1</ActionType>
    <LimitationName />
    <Code1>175</Code1>
    <Code2>0</Code2>
    <Code3>0</Code3>
    <StartDatetime>1900-01-01T00:00:00+06:00</StartDatetime>
    <StopDatetime>9999-12-31T00:00:00+07:00</StopDatetime>
  </Limitation>
  <Limitation>
    <LimitationKey>228759</LimitationKey>
    <LimitationObjectType>11</LimitationObjectType>
    <LimitationObjectKey>436040</LimitationObjectKey>
    <LimitationValue>(22178,54001,54002,54003,54004,54005,54006,54007,54008,54010,54011,54012,54013,54014,54015,54016,54017,54019,54020,54021,54022,54024,54025,54026,54027,54028,54029,54030,54031,54032,54034,54035,54036,54037,54038,54039,54040,54041,54043,54044,54047,54050,54051,54052,54055,54056,54057,54058,54060,54061,54064,54066,54080,54081,54083,54084,54085,54086,54087,54088,54089,54090,54091,54092,54704,54715,54793,54901,54902,54903,54904,54905,54906,54907,54908,54909,54910,54911,54912,54913,54914,54915,54916,54917,54918,55001,55013)</LimitationValue>
    <LimitationType>2</LimitationType>
    <ActionType>1</ActionType>
    <LimitationName />
    <Code1>175</Code1>
    <Code2>4898</Code2>
    <Code3>335</Code3>
    <StartDatetime>1900-01-01T00:00:00+06:00</StartDatetime>
    <StopDatetime>9999-12-31T00:00:00+07:00</StopDatetime>
  </Limitation>
  <Limitation>
    <LimitationKey>228768</LimitationKey>
    <LimitationObjectType>11</LimitationObjectType>
    <LimitationObjectKey>436045</LimitationObjectKey>
    <LimitationValue>(54001,54002,54003,54004,54005,54006,54007,54008,54010,54011,54012,54013,54014,54015,54016,54017,54019,54020,54021,54022,54024,54025,54026,54027,54028,54029,54030,54031,54032,54034,54035,54036,54037,54038,54039,54040,54041,54043,54044,54047,54050,54051,54052,54055,54056,54057,54058,54060,54061,54064,54066,54080,54081,54083,54084,54085,54086,54087,54088,54089,54090,54091,54092,54704,54715,54793,54901,54902,54903,54904,54905,54906,54907,54908,54909,54910,54911,54912,54913,54914,54915,54916,54917,54918,55001,55013)</LimitationValue>
    <LimitationType>2</LimitationType>
    <ActionType>1</ActionType>
    <LimitationName />
    <Code1>175</Code1>
    <Code2>4898</Code2>
    <Code3>340</Code3>
    <StartDatetime>1900-01-01T00:00:00+06:00</StartDatetime>
    <StopDatetime>9999-12-31T00:00:00+07:00</StopDatetime>
  </Limitation>
  <Limitation>
    <LimitationKey>228761</LimitationKey>
    <LimitationObjectType>11</LimitationObjectType>
    <LimitationObjectKey>436041</LimitationObjectKey>
    <LimitationValue>(22178,54001,54002,54003,54004,54005,54006,54007,54008,54010,54011,54012,54013,54014,54015,54016,54017,54019,54020,54021,54022,54024,54025,54026,54027,54028,54029,54030,54031,54032,54034,54035,54036,54037,54038,54039,54040,54041,54043,54044,54047,54050,54051,54052,54055,54056,54057,54058,54060,54061,54064,54066,54080,54081,54083,54084,54085,54086,54087,54088,54089,54090,54091,54092,54704,54715,54793,54901,54902,54903,54904,54905,54906,54907,54908,54909,54910,54911,54912,54913,54914,54915,54916,54917,54918,55001,55013)</LimitationValue>
    <LimitationType>2</LimitationType>
    <ActionType>1</ActionType>
    <LimitationName />
    <Code1>175</Code1>
    <Code2>4898</Code2>
    <Code3>336</Code3>
    <StartDatetime>1900-01-01T00:00:00+06:00</StartDatetime>
    <StopDatetime>9999-12-31T00:00:00+07:00</StopDatetime>
  </Limitation>
  <Limitation>
    <LimitationKey>228765</LimitationKey>
    <LimitationObjectType>11</LimitationObjectType>
    <LimitationObjectKey>436043</LimitationObjectKey>
    <LimitationValue>(22178,54001,54002,54003,54004,54005,54006,54007,54008,54010,54011,54012,54013,54014,54015,54016,54017,54019,54020,54021,54022,54024,54025,54026,54027,54028,54029,54030,54031,54032,54034,54035,54036,54037,54038,54039,54040,54041,54043,54044,54047,54050,54051,54052,54055,54056,54057,54058,54060,54061,54064,54066,54080,54081,54083,54084,54085,54086,54087,54088,54089,54090,54091,54092,54704,54715,54793,54901,54902,54903,54904,54905,54906,54907,54908,54909,54910,54911,54912,54913,54914,54915,54916,54917,54918,55001,55013)</LimitationValue>
    <LimitationType>2</LimitationType>
    <ActionType>1</ActionType>
    <LimitationName />
    <Code1>175</Code1>
    <Code2>4898</Code2>
    <Code3>338</Code3>
    <StartDatetime>1900-01-01T00:00:00+06:00</StartDatetime>
    <StopDatetime>9999-12-31T00:00:00+07:00</StopDatetime>
  </Limitation>
  <Limitation>
    <LimitationKey>228763</LimitationKey>
    <LimitationObjectType>11</LimitationObjectType>
    <LimitationObjectKey>436042</LimitationObjectKey>
    <LimitationValue>(22178,54001,54002,54003,54004,54005,54006,54007,54008,54010,54011,54012,54013,54014,54015,54016,54017,54019,54020,54021,54022,54024,54025,54026,54027,54028,54029,54030,54031,54032,54034,54035,54036,54037,54038,54039,54040,54041,54043,54044,54047,54050,54051,54052,54055,54056,54057,54058,54060,54061,54064,54066,54080,54081,54083,54084,54085,54086,54087,54088,54089,54090,54091,54092,54704,54715,54793,54901,54902,54903,54904,54905,54906,54907,54908,54909,54910,54911,54912,54913,54914,54915,54916,54917,54918,55001,55013)</LimitationValue>
    <LimitationType>2</LimitationType>
    <ActionType>1</ActionType>
    <LimitationName />
    <Code1>175</Code1>
    <Code2>4898</Code2>
    <Code3>337</Code3>
    <StartDatetime>1900-01-01T00:00:00+06:00</StartDatetime>
    <StopDatetime>9999-12-31T00:00:00+07:00</StopDatetime>
  </Limitation>
  <Limitation>
    <LimitationKey>228774</LimitationKey>
    <LimitationObjectType>11</LimitationObjectType>
    <LimitationObjectKey>436047</LimitationObjectKey>
    <LimitationValue>(54001,54002,54003,54004,54005,54006,54007,54008,54010,54011,54012,54013,54014,54015,54016,54017,54019,54020,54021,54022,54024,54025,54026,54027,54028,54029,54030,54031,54032,54034,54035,54036,54037,54038,54039,54040,54041,54043,54044,54047,54050,54051,54052,54055,54056,54057,54058,54060,54061,54064,54066,54080,54081,54083,54084,54085,54086,54087,54088,54089,54090,54091,54092,54704,54715,54793,54901,54902,54903,54904,54905,54906,54907,54908,54909,54910,54911,54912,54913,54914,54915,54916,54917,54918,55001,55013)</LimitationValue>
    <LimitationType>2</LimitationType>
    <ActionType>1</ActionType>
    <LimitationName />
    <Code1>175</Code1>
    <Code2>4898</Code2>
    <Code3>342</Code3>
    <StartDatetime>1900-01-01T00:00:00+06:00</StartDatetime>
    <StopDatetime>9999-12-31T00:00:00+07:00</StopDatetime>
  </Limitation>
  <Limitation>
    <LimitationKey>228771</LimitationKey>
    <LimitationObjectType>11</LimitationObjectType>
    <LimitationObjectKey>436048</LimitationObjectKey>
    <LimitationValue>(54001,54002,54003,54004,54005,54006,54007,54008,54010,54011,54012,54013,54014,54015,54016,54017,54019,54020,54021,54022,54024,54025,54026,54027,54028,54029,54030,54031,54032,54034,54035,54036,54037,54038,54039,54040,54041,54043,54044,54047,54050,54051,54052,54055,54056,54057,54058,54060,54061,54064,54066,54080,54081,54083,54084,54085,54086,54087,54088,54089,54090,54091,54092,54704,54715,54793,54901,54902,54903,54904,54905,54906,54907,54908,54909,54910,54911,54912,54913,54914,54915,54916,54917,54918,55001,55013)</LimitationValue>
    <LimitationType>2</LimitationType>
    <ActionType>1</ActionType>
    <LimitationName />
    <Code1>175</Code1>
    <Code2>4898</Code2>
    <Code3>343</Code3>
    <StartDatetime>1900-01-01T00:00:00+06:00</StartDatetime>
    <StopDatetime>9999-12-31T00:00:00+07:00</StopDatetime>
  </Limitation>
  <Limitation>
    <LimitationKey>228810</LimitationKey>
    <LimitationObjectType>11</LimitationObjectType>
    <LimitationObjectKey>436053</LimitationObjectKey>
    <LimitationValue>(22178)</LimitationValue>
    <LimitationType>2</LimitationType>
    <ActionType>1</ActionType>
    <LimitationName />
    <Code1>175</Code1>
    <Code2>4898</Code2>
    <Code3>348</Code3>
    <StartDatetime>1900-01-01T00:00:00+06:00</StartDatetime>
    <StopDatetime>9999-12-31T00:00:00+07:00</StopDatetime>
  </Limitation>
  <Limitation>
    <LimitationKey>228813</LimitationKey>
    <LimitationObjectType>11</LimitationObjectType>
    <LimitationObjectKey>426277</LimitationObjectKey>
    <LimitationValue>(54001,54002,54003,54004,54005,54006,54007,54008,54010,54011,54012,54013,54014,54015,54016,54017,54019,54020,54021,54022,54024,54025,54026,54027,54028,54029,54030,54031,54032,54034,54035,54036,54037,54038,54039,54040,54041,54043,54044,54047,54050,54051,54052,54055,54056,54057,54058,54060,54061,54064,54066,54080,54081,54083,54084,54085,54086,54087,54088,54089,54090,54091,54092,54704,54715,54793,54901,54902,54903,54904,54905,54906,54907,54908,54909,54910,54911,54912,54913,54914,54915,54916,54917,54918,55001,55013)</LimitationValue>
    <LimitationType>2</LimitationType>
    <ActionType>1</ActionType>
    <LimitationName />
    <Code1>175</Code1>
    <Code2>4898</Code2>
    <Code3>231</Code3>
    <StartDatetime>1900-01-01T00:00:00+06:00</StartDatetime>
    <StopDatetime>9999-12-31T00:00:00+07:00</StopDatetime>
  </Limitation>
  <Limitation>
    <LimitationKey>228815</LimitationKey>
    <LimitationObjectType>11</LimitationObjectType>
    <LimitationObjectKey>426817</LimitationObjectKey>
    <LimitationValue>(54001,54002,54003,54004,54005,54006,54007,54008,54010,54011,54012,54013,54014,54015,54016,54017,54019,54020,54021,54022,54024,54025,54026,54027,54028,54029,54030,54031,54032,54034,54035,54036,54037,54038,54039,54040,54041,54043,54044,54047,54050,54051,54052,54055,54056,54057,54058,54060,54061,54064,54066,54080,54081,54083,54084,54085,54086,54087,54088,54089,54090,54091,54092,54704,54715,54793,54901,54902,54903,54904,54905,54906,54907,54908,54909,54910,54911,54912,54913,54914,54915,54916,54917,54918,55001,55013)</LimitationValue>
    <LimitationType>2</LimitationType>
    <ActionType>1</ActionType>
    <LimitationName />
    <Code1>175</Code1>
    <Code2>4898</Code2>
    <Code3>248</Code3>
    <StartDatetime>1900-01-01T00:00:00+06:00</StartDatetime>
    <StopDatetime>9999-12-31T00:00:00+07:00</StopDatetime>
  </Limitation>
  <Limitation>
    <LimitationKey>228827</LimitationKey>
    <LimitationObjectType>11</LimitationObjectType>
    <LimitationObjectKey>420166</LimitationObjectKey>
    <LimitationValue>(22170,22179,22180,22181,22191,22193,22502,22801,22802)</LimitationValue>
    <LimitationType>2</LimitationType>
    <ActionType>2</ActionType>
    <LimitationName />
    <Code1>175</Code1>
    <Code2>4898</Code2>
    <Code3>48</Code3>
    <StartDatetime>1900-01-01T00:00:00+06:00</StartDatetime>
    <StopDatetime>9999-12-31T00:00:00+07:00</StopDatetime>
  </Limitation>
  <Limitation>
    <LimitationKey>228832</LimitationKey>
    <LimitationObjectType>11</LimitationObjectType>
    <LimitationObjectKey>425674</LimitationObjectKey>
    <LimitationValue>(22170,22179,22180,22181,22191,22193,22502,22801,22802)</LimitationValue>
    <LimitationType>2</LimitationType>
    <ActionType>2</ActionType>
    <LimitationName />
    <Code1>175</Code1>
    <Code2>4898</Code2>
    <Code3>201</Code3>
    <StartDatetime>1900-01-01T00:00:00+06:00</StartDatetime>
    <StopDatetime>9999-12-31T00:00:00+07:00</StopDatetime>
  </Limitation>
  <Limitation>
    <LimitationKey>228829</LimitationKey>
    <LimitationObjectType>11</LimitationObjectType>
    <LimitationObjectKey>426811</LimitationObjectKey>
    <LimitationValue>(22170,22179,22180,22181,22191,22193,22502,22801,22802)</LimitationValue>
    <LimitationType>2</LimitationType>
    <ActionType>2</ActionType>
    <LimitationName />
    <Code1>175</Code1>
    <Code2>4898</Code2>
    <Code3>242</Code3>
    <StartDatetime>1900-01-01T00:00:00+06:00</StartDatetime>
    <StopDatetime>9999-12-31T00:00:00+07:00</StopDatetime>
  </Limitation>
  <Limitation>
    <LimitationKey>228831</LimitationKey>
    <LimitationObjectType>11</LimitationObjectType>
    <LimitationObjectKey>425673</LimitationObjectKey>
    <LimitationValue>(22170,22179,22180,22181,22191,22193,22502,22801,22802)</LimitationValue>
    <LimitationType>2</LimitationType>
    <ActionType>2</ActionType>
    <LimitationName />
    <Code1>175</Code1>
    <Code2>4898</Code2>
    <Code3>200</Code3>
    <StartDatetime>1900-01-01T00:00:00+06:00</StartDatetime>
    <StopDatetime>9999-12-31T00:00:00+07:00</StopDatetime>
  </Limitation>
  <Limitation>
    <LimitationKey>228838</LimitationKey>
    <LimitationObjectType>11</LimitationObjectType>
    <LimitationObjectKey>420198</LimitationObjectKey>
    <LimitationValue>(22170,22179,22180,22181,22191,22193,22502,22801,22802)</LimitationValue>
    <LimitationType>2</LimitationType>
    <ActionType>2</ActionType>
    <LimitationName />
    <Code1>175</Code1>
    <Code2>4898</Code2>
    <Code3>80</Code3>
    <StartDatetime>1900-01-01T00:00:00+06:00</StartDatetime>
    <StopDatetime>9999-12-31T00:00:00+07:00</StopDatetime>
  </Limitation>
  <Limitation>
    <LimitationKey>228839</LimitationKey>
    <LimitationObjectType>11</LimitationObjectType>
    <LimitationObjectKey>422984</LimitationObjectKey>
    <LimitationValue>(22170,22179,22180,22181,22191,22193,22502,22801,22802)</LimitationValue>
    <LimitationType>2</LimitationType>
    <ActionType>2</ActionType>
    <LimitationName />
    <Code1>175</Code1>
    <Code2>4898</Code2>
    <Code3>111</Code3>
    <StartDatetime>1900-01-01T00:00:00+06:00</StartDatetime>
    <StopDatetime>9999-12-31T00:00:00+07:00</StopDatetime>
  </Limitation>
  <Limitation>
    <LimitationKey>228840</LimitationKey>
    <LimitationObjectType>11</LimitationObjectType>
    <LimitationObjectKey>422978</LimitationObjectKey>
    <LimitationValue>(22170,22179,22180,22181,22191,22193,22502,22801,22802)</LimitationValue>
    <LimitationType>2</LimitationType>
    <ActionType>2</ActionType>
    <LimitationName />
    <Code1>175</Code1>
    <Code2>4898</Code2>
    <Code3>105</Code3>
    <StartDatetime>1900-01-01T00:00:00+06:00</StartDatetime>
    <StopDatetime>9999-12-31T00:00:00+07:00</StopDatetime>
  </Limitation>
  <Limitation>
    <LimitationKey>228841</LimitationKey>
    <LimitationObjectType>11</LimitationObjectType>
    <LimitationObjectKey>430844</LimitationObjectKey>
    <LimitationValue>(22170,22179,22180,22181,22191,22193,22502,22801,22802)</LimitationValue>
    <LimitationType>2</LimitationType>
    <ActionType>2</ActionType>
    <LimitationName />
    <Code1>175</Code1>
    <Code2>4898</Code2>
    <Code3>305</Code3>
    <StartDatetime>1900-01-01T00:00:00+06:00</StartDatetime>
    <StopDatetime>9999-12-31T00:00:00+07:00</StopDatetime>
  </Limitation>
  <Limitation>
    <LimitationKey>228851</LimitationKey>
    <LimitationObjectType>11</LimitationObjectType>
    <LimitationObjectKey>425598</LimitationObjectKey>
    <LimitationValue>(22170,22179,22180,22181,22191,22193,22502,22801,22802)</LimitationValue>
    <LimitationType>2</LimitationType>
    <ActionType>2</ActionType>
    <LimitationName />
    <Code1>175</Code1>
    <Code2>4898</Code2>
    <Code3>178</Code3>
    <StartDatetime>1900-01-01T00:00:00+06:00</StartDatetime>
    <StopDatetime>9999-12-31T00:00:00+07:00</StopDatetime>
  </Limitation>
  <Limitation>
    <LimitationKey>228906</LimitationKey>
    <LimitationObjectType>11</LimitationObjectType>
    <LimitationObjectKey>443727</LimitationObjectKey>
    <LimitationValue>(54016)</LimitationValue>
    <LimitationType>2</LimitationType>
    <ActionType>1</ActionType>
    <LimitationName />
    <Code1>175</Code1>
    <Code2>6720</Code2>
    <Code3>1</Code3>
    <StartDatetime>1900-01-01T00:00:00+06:00</StartDatetime>
    <StopDatetime>9999-12-31T00:00:00+07:00</StopDatetime>
  </Limitation>
  <Limitation>
    <LimitationKey>229711</LimitationKey>
    <LimitationObjectType>3</LimitationObjectType>
    <LimitationObjectKey>6842</LimitationObjectKey>
    <LimitationValue>(42162)</LimitationValue>
    <LimitationType>2</LimitationType>
    <ActionType>1</ActionType>
    <LimitationName />
    <Code1>175</Code1>
    <Code2>6839</Code2>
    <Code3>0</Code3>
    <StartDatetime>1900-01-01T00:00:00+06:00</StartDatetime>
    <StopDatetime>9999-12-31T00:00:00+07:00</StopDatetime>
  </Limitation>
  <Limitation>
    <LimitationKey>229169</LimitationKey>
    <LimitationObjectType>3</LimitationObjectType>
    <LimitationObjectKey>6766</LimitationObjectKey>
    <LimitationValue>(42015)</LimitationValue>
    <LimitationType>2</LimitationType>
    <ActionType>1</ActionType>
    <LimitationName />
    <Code1>175</Code1>
    <Code2>6763</Code2>
    <Code3>0</Code3>
    <StartDatetime>1900-01-01T00:00:00+06:00</StartDatetime>
    <StopDatetime>9999-12-31T00:00:00+07:00</StopDatetime>
  </Limitation>
  <Limitation>
    <LimitationKey>230346</LimitationKey>
    <LimitationObjectType>11</LimitationObjectType>
    <LimitationObjectKey>461025</LimitationObjectKey>
    <LimitationValue>(54012,54085)</LimitationValue>
    <LimitationType>2</LimitationType>
    <ActionType>1</ActionType>
    <LimitationName />
    <Code1>175</Code1>
    <Code2>4897</Code2>
    <Code3>205</Code3>
    <StartDatetime>1900-01-01T00:00:00+06:00</StartDatetime>
    <StopDatetime>9999-12-31T00:00:00+07:00</StopDatetime>
  </Limitation>
  <Limitation>
    <LimitationKey>231786</LimitationKey>
    <LimitationObjectType>11</LimitationObjectType>
    <LimitationObjectKey>446025</LimitationObjectKey>
    <LimitationValue>(22142)</LimitationValue>
    <LimitationType>2</LimitationType>
    <ActionType>1</ActionType>
    <LimitationName />
    <Code1>175</Code1>
    <Code2>4898</Code2>
    <Code3>523</Code3>
    <StartDatetime>1900-01-01T00:00:00+06:00</StartDatetime>
    <StopDatetime>9999-12-31T00:00:00+07:00</StopDatetime>
  </Limitation>
</NewDataSet>